{
  "@id": "https://data.datatourisme.gouv.fr/15/5dcec0f6-9c3e-31a1-8f0f-eb9a50c18cab",
  "dc:identifier": "DEGCEN041V5002KM",
  "@type": [
    "schema:LocalBusiness",
    "schema:Product",
    "PlaceOfInterest",
    "PointOfInterest",
    "Practice",
    "Product",
    "Tasting",
    "TastingProvider",
    "WineCellar"
  ],
  "rdfs:comment": {
    "en": [
      "Young winemaker, making products independently since 2009. 20-ha domain on the banks of the Cher, which falls within the touraine and touraine chenonceaux appellations."
    ],
    "fr": [
      "Viticultrice indépendante depuis 2009, je vous accueille sur mon domaine, labellisé Terra Vitis, de 20 ha situé sur les coteaux du Cher en appellation Touraine et Touraine Chenonceaux. Afin de découvrir mes vins dans un cadre insolite, je vous propose de faire une balade avec Troglo Dégusto."
    ]
  },
  "rdfs:label": {
    "en": [
      "Domaine des Tabourelles"
    ],
    "fr": [
      "Domaine des Tabourelles"
    ]
  },
  "availableLanguage": [
    "en",
    "fr"
  ],
  "creationDate": "2014-10-23",
  "hasBeenCreatedBy": {
    "@id": "https://data.datatourisme.gouv.fr/07dc8557-cbf5-3300-8d81-6b0a558531c1",
    "schema:legalName": "ADT41",
    "@type": [
      "schema:Organization",
      "foaf:Agent",
      "Agent"
    ]
  },
  "hasBeenPublishedBy": [
    {
      "@id": "https://data.datatourisme.gouv.fr/bba35b4d-022c-3fa7-90a3-07eba818e3a5",
      "schema:legalName": "SIT Centre-Val de Loire",
      "@type": [
        "schema:Organization",
        "foaf:Agent",
        "Agent"
      ]
    }
  ],
  "hasBookingContact": [
    {
      "@id": "https://data.datatourisme.gouv.fr/5d6cf269-40e2-3a13-afcc-e2c222a185ae",
      "schema:email": [
        "contact.tabourelles@gmail.com"
      ],
      "schema:legalName": "Domaine des Tabourelles",
      "schema:telephone": [
        "+33 2 54 32 07 58",
        "+33 6 16 73 56 28"
      ],
      "@type": [
        "schema:Organization",
        "foaf:Agent",
        "Agent"
      ],
      "foaf:homepage": [
        "http://www.lestabourelles-leveret.com/"
      ]
    }
  ],
  "hasContact": [
    {
      "@id": "https://data.datatourisme.gouv.fr/5d6cf269-40e2-3a13-afcc-e2c222a185ae",
      "schema:email": [
        "contact.tabourelles@gmail.com"
      ],
      "schema:legalName": "Domaine des Tabourelles",
      "schema:telephone": [
        "+33 2 54 32 07 58",
        "+33 6 16 73 56 28"
      ],
      "@type": [
        "schema:Organization",
        "foaf:Agent",
        "Agent"
      ],
      "foaf:homepage": [
        "http://www.lestabourelles-leveret.com/"
      ]
    }
  ],
  "hasDescription": [
    {
      "@id": "https://data.datatourisme.gouv.fr/70fb1703-72cf-372b-9ef3-7ccba011a170",
      "dc:description": {
        "en": [
          "I am a young winemaker and have been making my products independently since 2009. I would be delighted to welcome you to my 20-ha estate on the slopes of the Cher, which falls within the Touraine and Touraine Chenonceaux appellations. Why not come to the unusual setting of Troglo Dégusto to discover my wines, where you will be offered a 1hr 30 min walk."
        ],
        "fr": [
          "Viticultrice  indépendante depuis 2009, je vous accueille sur mon domaine, labellisé Terra Vitis, de 20 ha situé sur les coteaux du Cher en appellation Touraine et Touraine Chenonceaux. Afin de découvrir mes vins dans un cadre insolite, je vous propose de faire une balade avec notre équipe Troglo Degusto qui vous conte 1500 ans d'histoire dans nos 35 kms de galeries souterrains, suivie d'une dégustation de 4 vins du Domaine avec de produits du Terroir ! Choisissez votre formule en découvrant les offres sur www.troglodegusto.fr."
        ]
      },
      "@type": [
        "Description"
      ],
      "shortDescription": {
        "en": [
          "Young winemaker, making products independently since 2009. 20-ha domain on the banks of the Cher, which falls within the touraine and touraine chenonceaux appellations."
        ],
        "fr": [
          "Viticultrice indépendante depuis 2009, je vous accueille sur mon domaine, labellisé Terra Vitis, de 20 ha situé sur les coteaux du Cher en appellation Touraine et Touraine Chenonceaux. Afin de découvrir mes vins dans un cadre insolite, je vous propose de faire une balade avec Troglo Dégusto."
        ]
      }
    }
  ],
  "hasFeature": [
    {
      "@id": "https://data.datatourisme.gouv.fr/d6701253-0020-348e-b2c0-79d3a5047d8b",
      "@type": [
        "schema:PropertyValue",
        "FeatureSpecification"
      ],
      "petsAllowed": true
    }
  ],
  "hasMainRepresentation": [
    {
      "@id": "https://data.datatourisme.gouv.fr/f874f7da-993c-3de1-bcea-0ea5e7f7ecfc",
      "ebucore:hasAnnotation": [
        {
          "@id": "https://data.datatourisme.gouv.fr/c122da78-b677-3390-8ddb-6d7ba1511ea1",
          "ebucore:title": {
            "fr": [
              "Troglo dégustation"
            ]
          },
          "@type": [
            "ebucore:Annotation",
            "Annotation"
          ],
          "credits": [
            "personnel"
          ],
          "rightsEndDate": "2028-12-24",
          "rightsStartDate": "2018-06-01"
        }
      ],
      "ebucore:hasRelatedResource": [
        {
          "@id": "https://data.datatourisme.gouv.fr/10cfe24a-05f2-3b36-8741-d5382e605571",
          "ebucore:hasMimeType": [
            {
              "@id": "kb:JPEG",
              "@type": [
                "ebucore:MimeType"
              ],
              "rdfs:comment": {
                "fr": [
                  "Image JPEG"
                ]
              },
              "rdfs:label": [
                "image/jpeg"
              ]
            }
          ],
          "ebucore:locator": [
            "https://centre.media.tourinsoft.eu/upload/Troglo-degustation.JPG"
          ],
          "@type": [
            "ebucore:Resource"
          ]
        }
      ],
      "@type": [
        "ebucore:EditorialObject"
      ]
    }
  ],
  "hasRepresentation": [
    {
      "@id": "https://data.datatourisme.gouv.fr/eb72227a-7bf0-3f99-a80f-5e436b1f941e",
      "ebucore:hasAnnotation": [
        {
          "@id": "https://data.datatourisme.gouv.fr/8dcff8fe-65c5-38d2-b164-5003686e21c6",
          "ebucore:title": {
            "fr": [
              "domaine-des-tabourelles"
            ]
          },
          "@type": [
            "ebucore:Annotation"
          ],
          "credits": [
            "domaine-des-tabourelles"
          ]
        }
      ],
      "ebucore:hasRelatedResource": [
        {
          "@id": "https://data.datatourisme.gouv.fr/4f230d60-0fe1-3468-aedf-3e244a0453bd",
          "ebucore:hasMimeType": [
            {
              "@id": "kb:JPEG",
              "@type": [
                "ebucore:MimeType"
              ],
              "rdfs:comment": {
                "fr": [
                  "Image JPEG"
                ]
              },
              "rdfs:label": [
                "image/jpeg"
              ]
            }
          ],
          "ebucore:locator": [
            "https://centre.media.tourinsoft.eu/upload/tabourelles-2020.jpg"
          ],
          "@type": [
            "ebucore:Resource"
          ]
        }
      ],
      "@type": [
        "ebucore:EditorialObject"
      ]
    },
    {
      "@id": "https://data.datatourisme.gouv.fr/f874f7da-993c-3de1-bcea-0ea5e7f7ecfc",
      "ebucore:hasAnnotation": [
        {
          "@id": "https://data.datatourisme.gouv.fr/c122da78-b677-3390-8ddb-6d7ba1511ea1",
          "ebucore:title": {
            "fr": [
              "Troglo dégustation"
            ]
          },
          "@type": [
            "ebucore:Annotation",
            "Annotation"
          ],
          "credits": [
            "personnel"
          ],
          "rightsEndDate": "2028-12-24",
          "rightsStartDate": "2018-06-01"
        }
      ],
      "ebucore:hasRelatedResource": [
        {
          "@id": "https://data.datatourisme.gouv.fr/10cfe24a-05f2-3b36-8741-d5382e605571",
          "ebucore:hasMimeType": [
            {
              "@id": "kb:JPEG",
              "@type": [
                "ebucore:MimeType"
              ],
              "rdfs:comment": {
                "fr": [
                  "Image JPEG"
                ]
              },
              "rdfs:label": [
                "image/jpeg"
              ]
            }
          ],
          "ebucore:locator": [
            "https://centre.media.tourinsoft.eu/upload/Troglo-degustation.JPG"
          ],
          "@type": [
            "ebucore:Resource"
          ]
        }
      ],
      "@type": [
        "ebucore:EditorialObject"
      ]
    }
  ],
  "hasReview": [
    {
      "@id": "https://data.datatourisme.gouv.fr/89ab7d1e-59f0-3c8d-ab2f-9875727b4fde",
      "@type": [
        "Review"
      ],
      "hasReviewValue": {
        "@id": "kb:LabelRating_BienvenueaLaFerme",
        "@type": [
          "LabelRating"
        ],
        "rdfs:label": {
          "en": [
            "Bienvenue à la ferme"
          ],
          "fr": [
            "Bienvenue à la ferme"
          ]
        },
        "isCompliantWith": [
          "CampingAndCaravanning",
          "Guesthouse",
          "Practice",
          "Restaurant",
          "SelfCateringAccommodation"
        ]
      }
    }
  ],
  "hasTheme": [
    {
      "@id": "kb:Wine",
      "@type": [
        "FoodProduct"
      ],
      "rdfs:label": {
        "en": [
          "Wine"
        ],
        "fr": [
          "Vin"
        ]
      }
    }
  ],
  "isLocatedAt": [
    {
      "@id": "https://data.datatourisme.gouv.fr/21e1f89a-0a90-3128-8d54-0b9b3e0180d9",
      "schema:address": [
        {
          "@id": "https://data.datatourisme.gouv.fr/39ed1489-bd3a-3a79-bfdb-edfe515c13b4",
          "schema:addressLocality": "Montrichard Val de Cher",
          "schema:postalCode": "41400",
          "schema:streetAddress": [
            "63 Route des Vallées"
          ],
          "@type": [
            "schema:PostalAddress",
            "PostalAddress"
          ],
          "hasAddressCity": [
            {
              "@id": "kb:41151",
              "@type": [
                "City"
              ],
              "rdfs:label": {
                "en": [
                  "Montrichard Val de Cher"
                ],
                "fr": [
                  "Montrichard Val de Cher"
                ]
              },
              "insee": "41151",
              "isPartOfDepartment": [
                {
                  "@id": "kb:France2441",
                  "@type": [
                    "Department"
                  ],
                  "rdfs:label": {
                    "en": [
                      "Loir-et-Cher"
                    ],
                    "fr": [
                      "Loir-et-Cher"
                    ]
                  },
                  "insee": "41",
                  "isPartOfRegion": [
                    {
                      "@id": "kb:France24",
                      "@type": [
                        "Region"
                      ],
                      "rdfs:label": {
                        "en": [
                          "Centre-Val de Loire"
                        ],
                        "fr": [
                          "Centre-Val de Loire"
                        ]
                      },
                      "insee": "24",
                      "isPartOfCountry": [
                        {
                          "@id": "kb:France",
                          "@type": [
                            "schema:Country"
                          ],
                          "rdfs:label": {
                            "en": [
                              "France"
                            ],
                            "fr": [
                              "France"
                            ]
                          }
                        }
                      ]
                    }
                  ]
                }
              ]
            }
          ]
        }
      ],
      "schema:geo": {
        "@id": "https://data.datatourisme.gouv.fr/e1795961-0df8-3356-9b71-42c4c31914ec",
        "schema:latitude": "47.3511922",
        "schema:longitude": "1.2333583",
        "@type": [
          "schema:GeoCoordinates"
        ]
      },
      "schema:openingHoursSpecification": [
        {
          "@id": "https://data.datatourisme.gouv.fr/167378aa-2804-3799-b856-6e79fb989753",
          "schema:closes": "12:30:00",
          "schema:dayOfWeek": [
            {
              "@id": "schema:Saturday",
              "@type": [
                "schema:DayOfWeek"
              ],
              "rdfs:label": {
                "en": [
                  "Saturday"
                ],
                "fr": [
                  "Samedi"
                ]
              }
            }
          ],
          "schema:opens": "10:00:00",
          "schema:validFrom": "2020-01-01T00:00:00",
          "schema:validThrough": "2020-12-31T00:00:00",
          "@type": [
            "schema:OpeningHoursSpecification"
          ]
        },
        {
          "@id": "https://data.datatourisme.gouv.fr/7414a99d-39d1-3340-9a43-056d30b79f3b",
          "schema:closes": "17:00:00",
          "schema:dayOfWeek": [
            {
              "@id": "schema:Wednesday",
              "@type": [
                "schema:DayOfWeek"
              ],
              "rdfs:label": {
                "en": [
                  "Wednesday"
                ],
                "fr": [
                  "Mercredi"
                ]
              }
            }
          ],
          "schema:opens": "14:00:00",
          "schema:validFrom": "2020-01-01T00:00:00",
          "schema:validThrough": "2020-12-31T00:00:00",
          "@type": [
            "schema:OpeningHoursSpecification"
          ]
        },
        {
          "@id": "https://data.datatourisme.gouv.fr/7da10917-51f6-3ea8-92c4-bfb2cf13b892",
          "schema:closes": "17:00:00",
          "schema:dayOfWeek": [
            {
              "@id": "schema:Friday",
              "@type": [
                "schema:DayOfWeek"
              ],
              "rdfs:label": {
                "en": [
                  "Friday"
                ],
                "fr": [
                  "Vendredi"
                ]
              }
            }
          ],
          "schema:opens": "14:00:00",
          "schema:validFrom": "2020-01-01T00:00:00",
          "schema:validThrough": "2020-12-31T00:00:00",
          "@type": [
            "schema:OpeningHoursSpecification"
          ]
        },
        {
          "@id": "https://data.datatourisme.gouv.fr/9b6ec8af-f48a-344d-96be-5d608fe71844",
          "schema:closes": "12:30:00",
          "schema:dayOfWeek": [
            {
              "@id": "schema:Tuesday",
              "@type": [
                "schema:DayOfWeek"
              ],
              "rdfs:label": {
                "en": [
                  "Tuesday"
                ],
                "fr": [
                  "Mardi"
                ]
              }
            }
          ],
          "schema:opens": "10:00:00",
          "schema:validFrom": "2020-01-01T00:00:00",
          "schema:validThrough": "2020-12-31T00:00:00",
          "@type": [
            "schema:OpeningHoursSpecification"
          ]
        },
        {
          "@id": "https://data.datatourisme.gouv.fr/ba35338b-2edc-3107-b9ea-db33eca96098",
          "schema:closes": "17:00:00",
          "schema:dayOfWeek": [
            {
              "@id": "schema:Tuesday",
              "@type": [
                "schema:DayOfWeek"
              ],
              "rdfs:label": {
                "en": [
                  "Tuesday"
                ],
                "fr": [
                  "Mardi"
                ]
              }
            }
          ],
          "schema:opens": "14:00:00",
          "schema:validFrom": "2020-01-01T00:00:00",
          "schema:validThrough": "2020-12-31T00:00:00",
          "@type": [
            "schema:OpeningHoursSpecification"
          ]
        },
        {
          "@id": "https://data.datatourisme.gouv.fr/de1b272b-80e4-329d-8410-a14d5a37f12e",
          "schema:closes": "12:30:00",
          "schema:dayOfWeek": [
            {
              "@id": "schema:Wednesday",
              "@type": [
                "schema:DayOfWeek"
              ],
              "rdfs:label": {
                "en": [
                  "Wednesday"
                ],
                "fr": [
                  "Mercredi"
                ]
              }
            }
          ],
          "schema:opens": "10:00:00",
          "schema:validFrom": "2020-01-01T00:00:00",
          "schema:validThrough": "2020-12-31T00:00:00",
          "@type": [
            "schema:OpeningHoursSpecification"
          ]
        },
        {
          "@id": "https://data.datatourisme.gouv.fr/e5d8e04b-a078-3f39-a530-44e9d85917c7",
          "schema:closes": "12:30:00",
          "schema:dayOfWeek": [
            {
              "@id": "schema:Friday",
              "@type": [
                "schema:DayOfWeek"
              ],
              "rdfs:label": {
                "en": [
                  "Friday"
                ],
                "fr": [
                  "Vendredi"
                ]
              }
            }
          ],
          "schema:opens": "10:00:00",
          "schema:validFrom": "2020-01-01T00:00:00",
          "schema:validThrough": "2020-12-31T00:00:00",
          "@type": [
            "schema:OpeningHoursSpecification"
          ]
        },
        {
          "@id": "https://data.datatourisme.gouv.fr/ed69d034-0277-3e6e-b771-380c8d637450",
          "schema:closes": "17:00:00",
          "schema:dayOfWeek": [
            {
              "@id": "schema:Thursday",
              "@type": [
                "schema:DayOfWeek"
              ],
              "rdfs:label": {
                "en": [
                  "Thursday"
                ],
                "fr": [
                  "Jeudi"
                ]
              }
            }
          ],
          "schema:opens": "14:00:00",
          "schema:validFrom": "2020-01-01T00:00:00",
          "schema:validThrough": "2020-12-31T00:00:00",
          "@type": [
            "schema:OpeningHoursSpecification"
          ]
        },
        {
          "@id": "https://data.datatourisme.gouv.fr/f0249d61-e783-3edb-81d9-9678b2bb715b",
          "schema:closes": "12:30:00",
          "schema:dayOfWeek": [
            {
              "@id": "schema:Thursday",
              "@type": [
                "schema:DayOfWeek"
              ],
              "rdfs:label": {
                "en": [
                  "Thursday"
                ],
                "fr": [
                  "Jeudi"
                ]
              }
            }
          ],
          "schema:opens": "10:00:00",
          "schema:validFrom": "2020-01-01T00:00:00",
          "schema:validThrough": "2020-12-31T00:00:00",
          "@type": [
            "schema:OpeningHoursSpecification"
          ]
        },
        {
          "@id": "https://data.datatourisme.gouv.fr/f64b198a-eec6-36be-bc36-fbb017e78e27",
          "schema:closes": "17:00:00",
          "schema:dayOfWeek": [
            {
              "@id": "schema:Saturday",
              "@type": [
                "schema:DayOfWeek"
              ],
              "rdfs:label": {
                "en": [
                  "Saturday"
                ],
                "fr": [
                  "Samedi"
                ]
              }
            }
          ],
          "schema:opens": "14:00:00",
          "schema:validFrom": "2020-01-01T00:00:00",
          "schema:validThrough": "2020-12-31T00:00:00",
          "@type": [
            "schema:OpeningHoursSpecification"
          ]
        }
      ],
      "@type": [
        "schema:Place",
        "Place"
      ],
      "petsAllowed": true
    }
  ],
  "lastUpdate": "2020-08-07",
  "lastUpdateDatatourisme": "2020-09-04T08:17:29.479Z",
  "offers": [
    {
      "@id": "https://data.datatourisme.gouv.fr/40f20366-c32b-37fc-b2e5-2913601cbb14",
      "schema:acceptedPaymentMethod": [
        {
          "@id": "kb:Cash",
          "@type": [
            "schema:PaymentMethod"
          ],
          "rdfs:label": {
            "en": [
              "Cash"
            ],
            "fr": [
              "Espèce"
            ]
          }
        },
        {
          "@id": "kb:Check",
          "@type": [
            "schema:PaymentMethod"
          ],
          "rdfs:label": {
            "en": [
              "Check"
            ],
            "fr": [
              "Chèque"
            ]
          }
        }
      ],
      "schema:priceSpecification": [
        {
          "@id": "https://data.datatourisme.gouv.fr/32f4b433-c98e-35ad-8983-560ad50c3ac4",
          "schema:minPrice": [
            "5"
          ],
          "schema:price": "5",
          "schema:priceCurrency": "EUR",
          "@type": [
            "schema:PriceSpecification",
            "PriceSpecification"
          ],
          "hasEligiblePolicy": {
            "@id": "kb:ChildRate",
            "@type": [
              "PricingPolicy"
            ],
            "rdfs:label": {
              "en": [
                "Child rate"
              ],
              "fr": [
                "Tarif enfant"
              ]
            }
          }
        },
        {
          "@id": "https://data.datatourisme.gouv.fr/83da4580-ab16-3e17-bd38-9365462f84d5",
          "schema:minPrice": [
            "11"
          ],
          "schema:price": "11",
          "schema:priceCurrency": "EUR",
          "@type": [
            "schema:PriceSpecification",
            "PriceSpecification"
          ],
          "hasEligiblePolicy": {
            "@id": "kb:BaseRateFullRate",
            "@type": [
              "PricingPolicy"
            ],
            "rdfs:label": {
              "en": [
                "Base rate - full rate"
              ],
              "fr": [
                "Tarif de base - plein tarif"
              ]
            }
          }
        }
      ],
      "@type": [
        "schema:Offer",
        "Offer"
      ]
    }
  ]
}