{
  "@id": "https://data.datatourisme.gouv.fr/15/4908286f-c761-3feb-9c6f-23f913ea633d",
  "dc:identifier": "ORG41AAOTS100026",
  "@type": [
    "schema:TouristInformationCenter",
    "PlaceOfInterest",
    "PointOfInterest",
    "TouristInformationCenter"
  ],
  "rdfs:comment": {
    "en": [
      "The tourist information center is in a historical place: the Augustinian monastery. This place allows casual visitors but also the people of the territory to discover a classified site. This space is both a venue for tourists and a place for information."
    ],
    "fr": [
      "Situé dans le musée Musikenfête, le Bureau d'information Touristique  vous accueille pour vous conseiller sur les sites à visiter, les animations... \nUne équipe disponible pour vous accueillir et vous aider dans la préparation de votre séjour ! Vous aimerez aussi nos circuits de randonnée."
    ]
  },
  "rdfs:label": {
    "en": [
      "Vallée Loir et Braye Tourist Office"
    ],
    "fr": [
      "Bureau d'information touristique à Montoire-sur-le-Loir"
    ]
  },
  "availableLanguage": [
    "en",
    "fr"
  ],
  "creationDate": "2010-01-01",
  "hasBeenCreatedBy": {
    "@id": "https://data.datatourisme.gouv.fr/07dc8557-cbf5-3300-8d81-6b0a558531c1",
    "schema:legalName": "ADT41",
    "@type": [
      "schema:Organization",
      "foaf:Agent",
      "Agent"
    ]
  },
  "hasBeenPublishedBy": [
    {
      "@id": "https://data.datatourisme.gouv.fr/bba35b4d-022c-3fa7-90a3-07eba818e3a5",
      "schema:legalName": "SIT Centre-Val de Loire",
      "@type": [
        "schema:Organization",
        "foaf:Agent",
        "Agent"
      ]
    }
  ],
  "hasBookingContact": [
    {
      "@id": "https://data.datatourisme.gouv.fr/6d0391f7-3e3c-312a-a511-47e9911183a0",
      "schema:address": [
        {
          "@id": "https://data.datatourisme.gouv.fr/c092811c-98a9-350e-9301-0e3518aafbcb",
          "schema:addressLocality": "Montoire-sur-le-Loir",
          "@type": [
            "schema:PostalAddress",
            "PostalAddress"
          ],
          "hasAddressCity": [
            {
              "@id": "kb:41149",
              "@type": [
                "City"
              ],
              "rdfs:label": {
                "en": [
                  "Montoire-sur-le-Loir"
                ],
                "fr": [
                  "Montoire-sur-le-Loir"
                ]
              },
              "insee": "41149",
              "isPartOfDepartment": [
                {
                  "@id": "kb:France2441",
                  "@type": [
                    "Department"
                  ],
                  "rdfs:label": {
                    "en": [
                      "Loir-et-Cher"
                    ],
                    "fr": [
                      "Loir-et-Cher"
                    ]
                  },
                  "insee": "41",
                  "isPartOfRegion": [
                    {
                      "@id": "kb:France24",
                      "@type": [
                        "Region"
                      ],
                      "rdfs:label": {
                        "en": [
                          "Centre-Val de Loire"
                        ],
                        "fr": [
                          "Centre-Val de Loire"
                        ]
                      },
                      "insee": "24",
                      "isPartOfCountry": [
                        {
                          "@id": "kb:France",
                          "@type": [
                            "schema:Country"
                          ],
                          "rdfs:label": {
                            "en": [
                              "France"
                            ],
                            "fr": [
                              "France"
                            ]
                          }
                        }
                      ]
                    }
                  ]
                }
              ]
            }
          ]
        }
      ],
      "schema:email": [
        "ot.vendome@wanadoo.fr"
      ],
      "schema:telephone": [
        "+33 2 54 77 05 07"
      ],
      "@type": [
        "foaf:Agent",
        "Agent"
      ],
      "foaf:homepage": [
        "http://www.vendome-tourisme.fr/"
      ]
    }
  ],
  "hasContact": [
    {
      "@id": "https://data.datatourisme.gouv.fr/6d0391f7-3e3c-312a-a511-47e9911183a0",
      "schema:address": [
        {
          "@id": "https://data.datatourisme.gouv.fr/c092811c-98a9-350e-9301-0e3518aafbcb",
          "schema:addressLocality": "Montoire-sur-le-Loir",
          "@type": [
            "schema:PostalAddress",
            "PostalAddress"
          ],
          "hasAddressCity": [
            {
              "@id": "kb:41149",
              "@type": [
                "City"
              ],
              "rdfs:label": {
                "en": [
                  "Montoire-sur-le-Loir"
                ],
                "fr": [
                  "Montoire-sur-le-Loir"
                ]
              },
              "insee": "41149",
              "isPartOfDepartment": [
                {
                  "@id": "kb:France2441",
                  "@type": [
                    "Department"
                  ],
                  "rdfs:label": {
                    "en": [
                      "Loir-et-Cher"
                    ],
                    "fr": [
                      "Loir-et-Cher"
                    ]
                  },
                  "insee": "41",
                  "isPartOfRegion": [
                    {
                      "@id": "kb:France24",
                      "@type": [
                        "Region"
                      ],
                      "rdfs:label": {
                        "en": [
                          "Centre-Val de Loire"
                        ],
                        "fr": [
                          "Centre-Val de Loire"
                        ]
                      },
                      "insee": "24",
                      "isPartOfCountry": [
                        {
                          "@id": "kb:France",
                          "@type": [
                            "schema:Country"
                          ],
                          "rdfs:label": {
                            "en": [
                              "France"
                            ],
                            "fr": [
                              "France"
                            ]
                          }
                        }
                      ]
                    }
                  ]
                }
              ]
            }
          ]
        }
      ],
      "schema:email": [
        "ot.vendome@wanadoo.fr"
      ],
      "schema:telephone": [
        "+33 2 54 77 05 07"
      ],
      "@type": [
        "foaf:Agent",
        "Agent"
      ],
      "foaf:homepage": [
        "http://www.vendome-tourisme.fr/"
      ]
    }
  ],
  "hasDescription": [
    {
      "@id": "https://data.datatourisme.gouv.fr/b9797a04-57c9-3b94-842c-c0af67af70d0",
      "dc:description": {
        "en": [
          "The tourist information center is now in a historical place: the Augustinian monastery. This place allows casual visitors but also the people of the territory to discover a classified place. This space is both a venue for tourists and a place for information."
        ],
        "fr": [
          "Situé dans le musée Musikenfête, le Bureau d'information Touristique  vous accueille pour vous conseiller sur les sites à visiter, les animations... \nUne équipe disponible pour vous accueillir et vous aider dans la préparation de votre séjour ! Vous aimerez aussi nos circuits de randonnée pédestre dans des paysages variés, entre Vallée du Loir et Perche, nos petites routes de campagne sur lesquelles vous pourrez vous balader à vélo."
        ]
      },
      "@type": [
        "Description"
      ],
      "shortDescription": {
        "en": [
          "The tourist information center is in a historical place: the Augustinian monastery. This place allows casual visitors but also the people of the territory to discover a classified site. This space is both a venue for tourists and a place for information."
        ],
        "fr": [
          "Situé dans le musée Musikenfête, le Bureau d'information Touristique  vous accueille pour vous conseiller sur les sites à visiter, les animations... \nUne équipe disponible pour vous accueillir et vous aider dans la préparation de votre séjour ! Vous aimerez aussi nos circuits de randonnée."
        ]
      }
    }
  ],
  "hasMainRepresentation": [
    {
      "@id": "https://data.datatourisme.gouv.fr/0a8ce3db-167b-3285-98f7-9d57f3fe34f2",
      "ebucore:hasAnnotation": [
        {
          "@id": "https://data.datatourisme.gouv.fr/8893e7ae-142d-36f4-85cf-69f605a4c949",
          "ebucore:title": {
            "fr": [
              "Bureau d'Information-Touristique-à-Montoire-sur-le-Loir"
            ]
          },
          "@type": [
            "ebucore:Annotation",
            "Annotation"
          ],
          "credits": [
            "Vendôme Tourisme"
          ],
          "rightsEndDate": "2020-12-31",
          "rightsStartDate": "2020-07-09"
        }
      ],
      "ebucore:hasRelatedResource": [
        {
          "@id": "https://data.datatourisme.gouv.fr/965f16c3-7a6a-306e-9f64-c4141608287c",
          "ebucore:hasMimeType": [
            {
              "@id": "kb:JPEG",
              "@type": [
                "ebucore:MimeType"
              ],
              "rdfs:comment": {
                "fr": [
                  "Image JPEG"
                ]
              },
              "rdfs:label": [
                "image/jpeg"
              ]
            }
          ],
          "ebucore:locator": [
            "https://centre.media.tourinsoft.eu/upload/BIT-Montoire-sur-le-Loir2-7a635f91f9b141cca8af7e7ff99fc0c3.jpg"
          ],
          "@type": [
            "ebucore:Resource"
          ]
        }
      ],
      "@type": [
        "ebucore:EditorialObject"
      ]
    }
  ],
  "hasRepresentation": [
    {
      "@id": "https://data.datatourisme.gouv.fr/0a8ce3db-167b-3285-98f7-9d57f3fe34f2",
      "ebucore:hasAnnotation": [
        {
          "@id": "https://data.datatourisme.gouv.fr/8893e7ae-142d-36f4-85cf-69f605a4c949",
          "ebucore:title": {
            "fr": [
              "Bureau d'Information-Touristique-à-Montoire-sur-le-Loir"
            ]
          },
          "@type": [
            "ebucore:Annotation",
            "Annotation"
          ],
          "credits": [
            "Vendôme Tourisme"
          ],
          "rightsEndDate": "2020-12-31",
          "rightsStartDate": "2020-07-09"
        }
      ],
      "ebucore:hasRelatedResource": [
        {
          "@id": "https://data.datatourisme.gouv.fr/965f16c3-7a6a-306e-9f64-c4141608287c",
          "ebucore:hasMimeType": [
            {
              "@id": "kb:JPEG",
              "@type": [
                "ebucore:MimeType"
              ],
              "rdfs:comment": {
                "fr": [
                  "Image JPEG"
                ]
              },
              "rdfs:label": [
                "image/jpeg"
              ]
            }
          ],
          "ebucore:locator": [
            "https://centre.media.tourinsoft.eu/upload/BIT-Montoire-sur-le-Loir2-7a635f91f9b141cca8af7e7ff99fc0c3.jpg"
          ],
          "@type": [
            "ebucore:Resource"
          ]
        }
      ],
      "@type": [
        "ebucore:EditorialObject"
      ]
    },
    {
      "@id": "https://data.datatourisme.gouv.fr/18358659-40b8-30ca-aa0f-b673bc144a33",
      "ebucore:hasAnnotation": [
        {
          "@id": "https://data.datatourisme.gouv.fr/c196d187-ffd3-31cf-be46-81755515142e",
          "ebucore:title": {
            "fr": [
              "Bureau d'Information-Touristique-à-Montoire-sur-le-Loir"
            ]
          },
          "@type": [
            "ebucore:Annotation",
            "Annotation"
          ],
          "credits": [
            "Vendôme Tourisme"
          ],
          "rightsEndDate": "2020-12-31",
          "rightsStartDate": "2020-07-21"
        }
      ],
      "ebucore:hasRelatedResource": [
        {
          "@id": "https://data.datatourisme.gouv.fr/c66525bf-007d-3050-8d8f-9f8092b1d3a3",
          "ebucore:hasMimeType": [
            {
              "@id": "kb:JPEG",
              "@type": [
                "ebucore:MimeType"
              ],
              "rdfs:comment": {
                "fr": [
                  "Image JPEG"
                ]
              },
              "rdfs:label": [
                "image/jpeg"
              ]
            }
          ],
          "ebucore:locator": [
            "https://centre.media.tourinsoft.eu/upload/20200721-152436.jpg"
          ],
          "@type": [
            "ebucore:Resource"
          ]
        }
      ],
      "@type": [
        "ebucore:EditorialObject"
      ]
    },
    {
      "@id": "https://data.datatourisme.gouv.fr/e2948aa4-a70f-3d09-9bcd-44cd3bb4f360",
      "ebucore:hasAnnotation": [
        {
          "@id": "https://data.datatourisme.gouv.fr/c196d187-ffd3-31cf-be46-81755515142e",
          "ebucore:title": {
            "fr": [
              "Bureau d'Information-Touristique-à-Montoire-sur-le-Loir"
            ]
          },
          "@type": [
            "ebucore:Annotation",
            "Annotation"
          ],
          "credits": [
            "Vendôme Tourisme"
          ],
          "rightsEndDate": "2020-12-31",
          "rightsStartDate": "2020-07-21"
        }
      ],
      "ebucore:hasRelatedResource": [
        {
          "@id": "https://data.datatourisme.gouv.fr/9be2b45b-a41d-37c9-b52a-46736afc7ce4",
          "ebucore:hasMimeType": [
            {
              "@id": "kb:JPEG",
              "@type": [
                "ebucore:MimeType"
              ],
              "rdfs:comment": {
                "fr": [
                  "Image JPEG"
                ]
              },
              "rdfs:label": [
                "image/jpeg"
              ]
            }
          ],
          "ebucore:locator": [
            "https://centre.media.tourinsoft.eu/upload/20200721-152444.jpg"
          ],
          "@type": [
            "ebucore:Resource"
          ]
        }
      ],
      "@type": [
        "ebucore:EditorialObject"
      ]
    },
    {
      "@id": "https://data.datatourisme.gouv.fr/ebc266b2-056a-3c2c-9eb9-71857e5111fc",
      "ebucore:hasAnnotation": [
        {
          "@id": "https://data.datatourisme.gouv.fr/c196d187-ffd3-31cf-be46-81755515142e",
          "ebucore:title": {
            "fr": [
              "Bureau d'Information-Touristique-à-Montoire-sur-le-Loir"
            ]
          },
          "@type": [
            "ebucore:Annotation",
            "Annotation"
          ],
          "credits": [
            "Vendôme Tourisme"
          ],
          "rightsEndDate": "2020-12-31",
          "rightsStartDate": "2020-07-21"
        }
      ],
      "ebucore:hasRelatedResource": [
        {
          "@id": "https://data.datatourisme.gouv.fr/25356553-fb96-3621-bd6d-8352cb177d40",
          "ebucore:hasMimeType": [
            {
              "@id": "kb:JPEG",
              "@type": [
                "ebucore:MimeType"
              ],
              "rdfs:comment": {
                "fr": [
                  "Image JPEG"
                ]
              },
              "rdfs:label": [
                "image/jpeg"
              ]
            }
          ],
          "ebucore:locator": [
            "https://centre.media.tourinsoft.eu/upload/20200721-172430.jpg"
          ],
          "@type": [
            "ebucore:Resource"
          ]
        }
      ],
      "@type": [
        "ebucore:EditorialObject"
      ]
    }
  ],
  "isLocatedAt": [
    {
      "@id": "https://data.datatourisme.gouv.fr/34031e44-f7d8-362d-ac1f-64f121cea71c",
      "schema:address": [
        {
          "@id": "https://data.datatourisme.gouv.fr/4add3b3f-3f82-38cb-b9b4-b07dc62b61a8",
          "schema:addressLocality": "Montoire-sur-le-Loir",
          "schema:postalCode": "41800",
          "schema:streetAddress": [
            "Rue Marescot"
          ],
          "@type": [
            "schema:PostalAddress",
            "PostalAddress"
          ],
          "hasAddressCity": [
            {
              "@id": "kb:41149",
              "@type": [
                "City"
              ],
              "rdfs:label": {
                "en": [
                  "Montoire-sur-le-Loir"
                ],
                "fr": [
                  "Montoire-sur-le-Loir"
                ]
              },
              "insee": "41149",
              "isPartOfDepartment": [
                {
                  "@id": "kb:France2441",
                  "@type": [
                    "Department"
                  ],
                  "rdfs:label": {
                    "en": [
                      "Loir-et-Cher"
                    ],
                    "fr": [
                      "Loir-et-Cher"
                    ]
                  },
                  "insee": "41",
                  "isPartOfRegion": [
                    {
                      "@id": "kb:France24",
                      "@type": [
                        "Region"
                      ],
                      "rdfs:label": {
                        "en": [
                          "Centre-Val de Loire"
                        ],
                        "fr": [
                          "Centre-Val de Loire"
                        ]
                      },
                      "insee": "24",
                      "isPartOfCountry": [
                        {
                          "@id": "kb:France",
                          "@type": [
                            "schema:Country"
                          ],
                          "rdfs:label": {
                            "en": [
                              "France"
                            ],
                            "fr": [
                              "France"
                            ]
                          }
                        }
                      ]
                    }
                  ]
                }
              ]
            }
          ]
        }
      ],
      "schema:geo": {
        "@id": "https://data.datatourisme.gouv.fr/1cb529d3-830c-3b3b-86a0-4010dd19973a",
        "schema:latitude": "47.7519625",
        "schema:longitude": "0.86154846",
        "@type": [
          "schema:GeoCoordinates"
        ]
      },
      "schema:openingHoursSpecification": [
        {
          "@id": "https://data.datatourisme.gouv.fr/17d19edf-64f9-322c-8a6d-02fc0df289df",
          "schema:closes": "12:00:00",
          "schema:dayOfWeek": [
            {
              "@id": "schema:Friday",
              "@type": [
                "schema:DayOfWeek"
              ],
              "rdfs:label": {
                "en": [
                  "Friday"
                ],
                "fr": [
                  "Vendredi"
                ]
              }
            }
          ],
          "schema:opens": "10:00:00",
          "schema:validFrom": "2020-09-08T00:00:00",
          "schema:validThrough": "2020-09-30T00:00:00",
          "@type": [
            "schema:OpeningHoursSpecification"
          ]
        },
        {
          "@id": "https://data.datatourisme.gouv.fr/3b73f0e9-291b-3236-9c1a-ec0f0f105274",
          "schema:closes": "12:00:00",
          "schema:dayOfWeek": [
            {
              "@id": "schema:Wednesday",
              "@type": [
                "schema:DayOfWeek"
              ],
              "rdfs:label": {
                "en": [
                  "Wednesday"
                ],
                "fr": [
                  "Mercredi"
                ]
              }
            }
          ],
          "schema:opens": "10:00:00",
          "schema:validFrom": "2020-09-08T00:00:00",
          "schema:validThrough": "2020-09-30T00:00:00",
          "@type": [
            "schema:OpeningHoursSpecification"
          ]
        },
        {
          "@id": "https://data.datatourisme.gouv.fr/3ebcee69-ecdc-3236-8b3c-bc2ecf10a52a",
          "schema:closes": "18:00:00",
          "schema:dayOfWeek": [
            {
              "@id": "schema:Friday",
              "@type": [
                "schema:DayOfWeek"
              ],
              "rdfs:label": {
                "en": [
                  "Friday"
                ],
                "fr": [
                  "Vendredi"
                ]
              }
            }
          ],
          "schema:opens": "14:00:00",
          "schema:validFrom": "2020-09-08T00:00:00",
          "schema:validThrough": "2020-09-30T00:00:00",
          "@type": [
            "schema:OpeningHoursSpecification"
          ]
        },
        {
          "@id": "https://data.datatourisme.gouv.fr/59e0b606-41ab-30a4-9ca7-393c9bc01332",
          "schema:closes": "12:00:00",
          "schema:dayOfWeek": [
            {
              "@id": "schema:Saturday",
              "@type": [
                "schema:DayOfWeek"
              ],
              "rdfs:label": {
                "en": [
                  "Saturday"
                ],
                "fr": [
                  "Samedi"
                ]
              }
            }
          ],
          "schema:opens": "10:00:00",
          "schema:validFrom": "2020-09-08T00:00:00",
          "schema:validThrough": "2020-09-30T00:00:00",
          "@type": [
            "schema:OpeningHoursSpecification"
          ]
        },
        {
          "@id": "https://data.datatourisme.gouv.fr/df508cad-d2ad-3add-b92a-266253dd20b2",
          "schema:closes": "18:00:00",
          "schema:dayOfWeek": [
            {
              "@id": "schema:Saturday",
              "@type": [
                "schema:DayOfWeek"
              ],
              "rdfs:label": {
                "en": [
                  "Saturday"
                ],
                "fr": [
                  "Samedi"
                ]
              }
            }
          ],
          "schema:opens": "14:00:00",
          "schema:validFrom": "2020-09-08T00:00:00",
          "schema:validThrough": "2020-09-30T00:00:00",
          "@type": [
            "schema:OpeningHoursSpecification"
          ]
        },
        {
          "@id": "https://data.datatourisme.gouv.fr/e31c271c-59ff-3b84-8369-a0e321f6df9e",
          "schema:closes": "18:00:00",
          "schema:dayOfWeek": [
            {
              "@id": "schema:Wednesday",
              "@type": [
                "schema:DayOfWeek"
              ],
              "rdfs:label": {
                "en": [
                  "Wednesday"
                ],
                "fr": [
                  "Mercredi"
                ]
              }
            }
          ],
          "schema:opens": "14:00:00",
          "schema:validFrom": "2020-09-08T00:00:00",
          "schema:validThrough": "2020-09-30T00:00:00",
          "@type": [
            "schema:OpeningHoursSpecification"
          ]
        }
      ],
      "@type": [
        "schema:Place",
        "Place"
      ]
    }
  ],
  "lastUpdate": "2020-09-01",
  "lastUpdateDatatourisme": "2020-09-07T23:45:23.518Z"
}