{
  "@id": "https://data.datatourisme.gouv.fr/15/3f03831d-91c6-3917-a73d-7095b8310155",
  "dc:identifier": "HCOCEN03700054",
  "@type": [
    "schema:LodgingBusiness",
    "Accommodation",
    "CollectiveAccommodation",
    "GroupLodging",
    "PlaceOfInterest",
    "PointOfInterest"
  ],
  "rdfs:comment": {
    "en": [
      "This fully renovated mill is the perfect base for visiting the Loire châteaux in the Tauxigny countryside just 10km from Loches. It is also near footpaths and the Loire & Indre by Bike paths. Ground floor: hallway (lift and 2 disabled toilets), small lounge, semi-professional equipped kitchen and la"
    ],
    "fr": [
      "Dans la campagne de Tauxigny, le long de la vallée de l’échandon, laissez vous séduire par ce moulin entièrement rénové. À 10 km de Loches, idéalement situé pour la visite des châteaux de la Loire, proche des sentiers de randonnées pédestres et des sentiers cyclistes de la Loire et de l’Indre à vélo"
    ]
  },
  "rdfs:label": {
    "en": [
      "Le Moulin de Ligoret"
    ],
    "fr": [
      "Le Moulin de Ligoret"
    ]
  },
  "allowedPersons": 37,
  "availableLanguage": [
    "en",
    "es",
    "fr"
  ],
  "creationDate": "2012-11-14",
  "hasBeenCreatedBy": {
    "@id": "https://data.datatourisme.gouv.fr/04c81750-b203-3927-9f84-c974baa96a0c",
    "schema:legalName": "Loches Touraine Châteaux de la Loire",
    "@type": [
      "schema:Organization",
      "foaf:Agent",
      "Agent"
    ]
  },
  "hasBeenPublishedBy": [
    {
      "@id": "https://data.datatourisme.gouv.fr/bba35b4d-022c-3fa7-90a3-07eba818e3a5",
      "schema:legalName": "SIT Centre-Val de Loire",
      "@type": [
        "schema:Organization",
        "foaf:Agent",
        "Agent"
      ]
    }
  ],
  "hasBookingContact": [
    {
      "@id": "https://data.datatourisme.gouv.fr/ae8782ec-edc3-3dd7-bd12-29789ad47a8b",
      "@type": [
        "foaf:Agent",
        "Agent"
      ],
      "foaf:homepage": [
        "http://www.moulindeligoret.fr/"
      ]
    }
  ],
  "hasContact": [
    {
      "@id": "https://data.datatourisme.gouv.fr/1cebfc3c-83d0-3b30-88b0-ea5c066b2e58",
      "schema:email": [
        "vacances@lasaulaie.fr"
      ],
      "schema:telephone": [
        "+33 2 47 92 51 46"
      ],
      "@type": [
        "foaf:Agent",
        "Agent"
      ],
      "foaf:homepage": [
        "http://www.moulindeligoret.fr/"
      ]
    },
    {
      "@id": "https://data.datatourisme.gouv.fr/ae8782ec-edc3-3dd7-bd12-29789ad47a8b",
      "@type": [
        "foaf:Agent",
        "Agent"
      ],
      "foaf:homepage": [
        "http://www.moulindeligoret.fr/"
      ]
    }
  ],
  "hasDescription": [
    {
      "@id": "https://data.datatourisme.gouv.fr/a850d90e-becf-3bb5-8a92-038b6903f28a",
      "dc:description": {
        "en": [
          "This fully renovated mill is the perfect base for visiting the Loire châteaux in the Tauxigny countryside just 10km from Loches. It is also near footpaths and the Loire & Indre by Bike paths. Ground floor: hallway (lift and 2 disabled toilets), small lounge, semi-professional equipped kitchen and large lounge. 3 upper floors: 11 bedrooms sleeping 36 (2, 3, 4 or 5 beds per bedroom), 9 bathrooms (inc. 5 disabled bathrooms) and 9 toilets."
        ],
        "fr": [
          "Dans la campagne de Tauxigny, le long de la vallée de l’échandon, laissez vous séduire par ce moulin entièrement rénové. À 10 km de Loches, idéalement situé pour la visite des châteaux de la Loire, proche des sentiers de randonnées pédestres et des sentiers cyclistes de la Loire et de l’Indre à vélo. Au RDC du Moulin, vous trouverez une entrée (avec l’ascendeur et 2 WC adaptés pour les personnes à mobilité réduite), un petit salon, la cuisine équipée semi professionnelle ainsi qu’une grande salle de réception. Aux 3 étages au dessus, vous trouverez 11 chambres pouvant accueillir 37 personnes (chambres de 2, 3, 4 et 6 personnes), 9 salles de bain et 9 WC, 5 de ces salles de bain sont accessibles aux personnes à mobilité réduite."
        ]
      },
      "@type": [
        "Description"
      ],
      "shortDescription": {
        "en": [
          "This fully renovated mill is the perfect base for visiting the Loire châteaux in the Tauxigny countryside just 10km from Loches. It is also near footpaths and the Loire & Indre by Bike paths. Ground floor: hallway (lift and 2 disabled toilets), small lounge, semi-professional equipped kitchen and la"
        ],
        "fr": [
          "Dans la campagne de Tauxigny, le long de la vallée de l’échandon, laissez vous séduire par ce moulin entièrement rénové. À 10 km de Loches, idéalement situé pour la visite des châteaux de la Loire, proche des sentiers de randonnées pédestres et des sentiers cyclistes de la Loire et de l’Indre à vélo"
        ]
      }
    }
  ],
  "hasFeature": [
    {
      "@id": "https://data.datatourisme.gouv.fr/15c9bc45-6519-3e37-8e87-7fb0b62a3862",
      "@type": [
        "schema:PropertyValue",
        "FeatureSpecification"
      ],
      "features": [
        {
          "@id": "kb:CommunalKitchen",
          "@type": [
            "AccommodationAmenity"
          ],
          "rdfs:label": {
            "en": [
              "Communal kitchen"
            ],
            "fr": [
              "Cuisine collective"
            ]
          }
        },
        {
          "@id": "kb:Elevator",
          "@type": [
            "CommonAmenity"
          ],
          "rdfs:label": {
            "en": [
              "Elevator"
            ],
            "fr": [
              "Ascenseur"
            ]
          }
        },
        {
          "@id": "kb:Garden",
          "@type": [
            "AccommodationAmenity"
          ],
          "rdfs:label": {
            "en": [
              "Garden"
            ],
            "fr": [
              "Jardin"
            ]
          }
        },
        {
          "@id": "kb:LinenHire",
          "@type": [
            "AccommodationAmenity"
          ],
          "rdfs:label": {
            "en": [
              "Linen hire"
            ],
            "fr": [
              "Location de linge"
            ]
          }
        },
        {
          "@id": "kb:LivingRoom",
          "@type": [
            "AccommodationAmenity"
          ],
          "rdfs:label": {
            "en": [
              "Living room"
            ],
            "fr": [
              "Coin salon"
            ]
          }
        },
        {
          "@id": "kb:LockedStorageRoom",
          "@type": [
            "CommonAmenity"
          ],
          "rdfs:label": {
            "en": [
              "Locked storage room"
            ],
            "fr": [
              "Local matériel fermé"
            ]
          }
        },
        {
          "@id": "kb:MeetingRoom",
          "@type": [
            "CommonAmenity"
          ],
          "rdfs:label": {
            "en": [
              "Meeting room"
            ],
            "fr": [
              "Salle de réunion"
            ]
          }
        },
        {
          "@id": "kb:Park",
          "@type": [
            "CommonAmenity"
          ],
          "rdfs:label": {
            "en": [
              "Park"
            ],
            "fr": [
              "Parc"
            ]
          }
        },
        {
          "@id": "kb:PrivateParking",
          "@type": [
            "CommonAmenity"
          ],
          "rdfs:label": {
            "en": [
              "Private parking"
            ],
            "fr": [
              "Parking privé"
            ]
          }
        },
        {
          "@id": "kb:ReceptionRoom",
          "@type": [
            "RoomAmenity"
          ],
          "rdfs:label": {
            "en": [
              "Reception room"
            ],
            "fr": [
              "Salle de réception"
            ]
          }
        },
        {
          "@id": "kb:SharedWasher",
          "@type": [
            "AccommodationAmenity"
          ],
          "rdfs:label": {
            "en": [
              "Shared washer"
            ],
            "fr": [
              "Lave linge collectif"
            ]
          }
        },
        {
          "@id": "kb:TVRoomArea",
          "@type": [
            "CommonAmenity"
          ],
          "rdfs:label": {
            "en": [
              "TV room or area"
            ],
            "fr": [
              "Salle ou coin TV"
            ]
          }
        },
        {
          "@id": "kb:Wifi",
          "@type": [
            "CommonAmenity"
          ],
          "rdfs:label": {
            "en": [
              "Wifi, internet access"
            ],
            "fr": [
              "Wifi, accès internet"
            ]
          }
        }
      ],
      "internetAccess": true,
      "petsAllowed": false
    }
  ],
  "hasMainRepresentation": [
    {
      "@id": "https://data.datatourisme.gouv.fr/44e35ffd-0209-3f7b-8660-326f66066a19",
      "ebucore:hasAnnotation": [
        {
          "@id": "https://data.datatourisme.gouv.fr/f587d85d-0307-3593-93c0-0ed55d3badd3",
          "ebucore:isCoveredBy": "oui",
          "ebucore:title": {
            "fr": [
              "Le Moulin de Ligoret"
            ]
          },
          "@type": [
            "ebucore:Annotation",
            "Annotation"
          ],
          "credits": [
            "Moulin du Ligoret"
          ],
          "rightsEndDate": "2029-12-31",
          "rightsStartDate": "2018-10-26"
        }
      ],
      "ebucore:hasRelatedResource": [
        {
          "@id": "https://data.datatourisme.gouv.fr/c41c62ec-5642-30f3-b496-d9a2e3efeaae",
          "ebucore:hasMimeType": [
            {
              "@id": "kb:JPEG",
              "@type": [
                "ebucore:MimeType"
              ],
              "rdfs:comment": {
                "fr": [
                  "Image JPEG"
                ]
              },
              "rdfs:label": [
                "image/jpeg"
              ]
            }
          ],
          "ebucore:locator": [
            "https://centre.media.tourinsoft.eu/upload/compIMG-9331.jpg"
          ],
          "@type": [
            "ebucore:Resource"
          ]
        }
      ],
      "@type": [
        "ebucore:EditorialObject"
      ]
    }
  ],
  "hasRepresentation": [
    {
      "@id": "https://data.datatourisme.gouv.fr/14ff5cb4-2b71-316d-bf1b-86923f8ec503",
      "ebucore:hasAnnotation": [
        {
          "@id": "https://data.datatourisme.gouv.fr/b5828380-4b14-3f43-bcfd-3f5ebf79b2f8",
          "ebucore:isCoveredBy": "oui",
          "ebucore:title": {
            "fr": [
              "compIMG_9379"
            ]
          },
          "@type": [
            "ebucore:Annotation",
            "Annotation"
          ],
          "credits": [
            "Moulin du Ligoret"
          ],
          "rightsEndDate": "2029-12-31",
          "rightsStartDate": "2018-10-26"
        }
      ],
      "ebucore:hasRelatedResource": [
        {
          "@id": "https://data.datatourisme.gouv.fr/feab5793-2c99-3c74-960e-c3d51ef85946",
          "ebucore:hasMimeType": [
            {
              "@id": "kb:JPEG",
              "@type": [
                "ebucore:MimeType"
              ],
              "rdfs:comment": {
                "fr": [
                  "Image JPEG"
                ]
              },
              "rdfs:label": [
                "image/jpeg"
              ]
            }
          ],
          "ebucore:locator": [
            "https://centre.media.tourinsoft.eu/upload/compIMG-9379.jpg"
          ],
          "@type": [
            "ebucore:Resource"
          ]
        }
      ],
      "@type": [
        "ebucore:EditorialObject"
      ]
    },
    {
      "@id": "https://data.datatourisme.gouv.fr/2e71db19-79b7-3f71-835c-e854419e51ed",
      "ebucore:hasAnnotation": [
        {
          "@id": "https://data.datatourisme.gouv.fr/d5e0105a-ffc5-3d8d-8f93-2c3305e68ee4",
          "ebucore:isCoveredBy": "oui",
          "ebucore:title": {
            "fr": [
              "compIMG_9356"
            ]
          },
          "@type": [
            "ebucore:Annotation",
            "Annotation"
          ],
          "credits": [
            "Moulin du Ligoret"
          ],
          "rightsEndDate": "2029-12-31",
          "rightsStartDate": "2018-10-26"
        }
      ],
      "ebucore:hasRelatedResource": [
        {
          "@id": "https://data.datatourisme.gouv.fr/a2a1741b-460d-3ab2-8c00-46cf274f2d18",
          "ebucore:hasMimeType": [
            {
              "@id": "kb:JPEG",
              "@type": [
                "ebucore:MimeType"
              ],
              "rdfs:comment": {
                "fr": [
                  "Image JPEG"
                ]
              },
              "rdfs:label": [
                "image/jpeg"
              ]
            }
          ],
          "ebucore:locator": [
            "https://centre.media.tourinsoft.eu/upload/compIMG-9356.jpg"
          ],
          "@type": [
            "ebucore:Resource"
          ]
        }
      ],
      "@type": [
        "ebucore:EditorialObject"
      ]
    },
    {
      "@id": "https://data.datatourisme.gouv.fr/43845ec8-50a8-3be7-96dd-3dc62f7f506e",
      "ebucore:hasAnnotation": [
        {
          "@id": "https://data.datatourisme.gouv.fr/1d9e1628-0798-36b7-b1e8-2d3247a3eae8",
          "ebucore:isCoveredBy": "oui",
          "ebucore:title": {
            "fr": [
              "compIMG_9309-2"
            ]
          },
          "@type": [
            "ebucore:Annotation",
            "Annotation"
          ],
          "credits": [
            "Moulin du Ligoret"
          ],
          "rightsEndDate": "2029-12-31",
          "rightsStartDate": "2018-10-26"
        }
      ],
      "ebucore:hasRelatedResource": [
        {
          "@id": "https://data.datatourisme.gouv.fr/5888b847-f551-3f8a-beac-d4ae8df0f72d",
          "ebucore:hasMimeType": [
            {
              "@id": "kb:JPEG",
              "@type": [
                "ebucore:MimeType"
              ],
              "rdfs:comment": {
                "fr": [
                  "Image JPEG"
                ]
              },
              "rdfs:label": [
                "image/jpeg"
              ]
            }
          ],
          "ebucore:locator": [
            "https://centre.media.tourinsoft.eu/upload/compIMG-9309-2.jpg"
          ],
          "@type": [
            "ebucore:Resource"
          ]
        }
      ],
      "@type": [
        "ebucore:EditorialObject"
      ]
    },
    {
      "@id": "https://data.datatourisme.gouv.fr/44e35ffd-0209-3f7b-8660-326f66066a19",
      "ebucore:hasAnnotation": [
        {
          "@id": "https://data.datatourisme.gouv.fr/f587d85d-0307-3593-93c0-0ed55d3badd3",
          "ebucore:isCoveredBy": "oui",
          "ebucore:title": {
            "fr": [
              "Le Moulin de Ligoret"
            ]
          },
          "@type": [
            "ebucore:Annotation",
            "Annotation"
          ],
          "credits": [
            "Moulin du Ligoret"
          ],
          "rightsEndDate": "2029-12-31",
          "rightsStartDate": "2018-10-26"
        }
      ],
      "ebucore:hasRelatedResource": [
        {
          "@id": "https://data.datatourisme.gouv.fr/c41c62ec-5642-30f3-b496-d9a2e3efeaae",
          "ebucore:hasMimeType": [
            {
              "@id": "kb:JPEG",
              "@type": [
                "ebucore:MimeType"
              ],
              "rdfs:comment": {
                "fr": [
                  "Image JPEG"
                ]
              },
              "rdfs:label": [
                "image/jpeg"
              ]
            }
          ],
          "ebucore:locator": [
            "https://centre.media.tourinsoft.eu/upload/compIMG-9331.jpg"
          ],
          "@type": [
            "ebucore:Resource"
          ]
        }
      ],
      "@type": [
        "ebucore:EditorialObject"
      ]
    },
    {
      "@id": "https://data.datatourisme.gouv.fr/c1af1edd-d3dd-3345-b0a7-9b4091405b6c",
      "ebucore:hasAnnotation": [
        {
          "@id": "https://data.datatourisme.gouv.fr/d4cfae68-b41d-3f34-9e8c-c08b6b58ef3b",
          "ebucore:isCoveredBy": "oui",
          "ebucore:title": {
            "fr": [
              "compIMG_9410"
            ]
          },
          "@type": [
            "ebucore:Annotation",
            "Annotation"
          ],
          "credits": [
            "Moulin du Ligoret"
          ],
          "rightsEndDate": "2029-12-31",
          "rightsStartDate": "2018-10-26"
        }
      ],
      "ebucore:hasRelatedResource": [
        {
          "@id": "https://data.datatourisme.gouv.fr/f5730fc1-21f4-3bb9-a684-16f53cbcc945",
          "ebucore:hasMimeType": [
            {
              "@id": "kb:JPEG",
              "@type": [
                "ebucore:MimeType"
              ],
              "rdfs:comment": {
                "fr": [
                  "Image JPEG"
                ]
              },
              "rdfs:label": [
                "image/jpeg"
              ]
            }
          ],
          "ebucore:locator": [
            "https://centre.media.tourinsoft.eu/upload/compIMG-9410.jpg"
          ],
          "@type": [
            "ebucore:Resource"
          ]
        }
      ],
      "@type": [
        "ebucore:EditorialObject"
      ]
    }
  ],
  "isLocatedAt": [
    {
      "@id": "https://data.datatourisme.gouv.fr/6b8f186c-9bd9-39a4-9e39-aba72b29f12c",
      "schema:address": [
        {
          "@id": "https://data.datatourisme.gouv.fr/601a7ce1-a559-31e7-9ab1-72e62db4b36b",
          "schema:addressLocality": "Tauxigny-Saint-Bauld",
          "schema:postalCode": "37310",
          "schema:streetAddress": [
            "Le Ligoret",
            "Le Moulin de Ligoret"
          ],
          "@type": [
            "schema:PostalAddress",
            "PostalAddress"
          ],
          "hasAddressCity": [
            {
              "@id": "kb:37254",
              "@type": [
                "City"
              ],
              "rdfs:label": {
                "en": [
                  "Tauxigny-Saint-Bauld"
                ],
                "fr": [
                  "Tauxigny-Saint-Bauld"
                ]
              },
              "insee": "37254",
              "isPartOfDepartment": [
                {
                  "@id": "kb:France2437",
                  "@type": [
                    "Department"
                  ],
                  "rdfs:label": {
                    "en": [
                      "Indre-et-Loire"
                    ],
                    "fr": [
                      "Indre-et-Loire"
                    ]
                  },
                  "insee": "37",
                  "isPartOfRegion": [
                    {
                      "@id": "kb:France24",
                      "@type": [
                        "Region"
                      ],
                      "rdfs:label": {
                        "en": [
                          "Centre-Val de Loire"
                        ],
                        "fr": [
                          "Centre-Val de Loire"
                        ]
                      },
                      "insee": "24",
                      "isPartOfCountry": [
                        {
                          "@id": "kb:France",
                          "@type": [
                            "schema:Country"
                          ],
                          "rdfs:label": {
                            "en": [
                              "France"
                            ],
                            "fr": [
                              "France"
                            ]
                          }
                        }
                      ]
                    }
                  ]
                }
              ]
            }
          ]
        }
      ],
      "schema:geo": {
        "@id": "https://data.datatourisme.gouv.fr/81418cea-7aef-3c9e-a33a-dd515c18f8d1",
        "schema:latitude": "47.2239526",
        "schema:longitude": "0.82997684",
        "@type": [
          "schema:GeoCoordinates"
        ]
      },
      "@type": [
        "schema:Place",
        "Place"
      ],
      "internetAccess": true,
      "petsAllowed": false
    }
  ],
  "lastUpdate": "2020-01-28",
  "lastUpdateDatatourisme": "2020-07-06T23:46:56.216Z",
  "offers": [
    {
      "@id": "https://data.datatourisme.gouv.fr/67ed5593-6811-3f9d-81f9-815e3b945a67",
      "schema:acceptedPaymentMethod": [
        {
          "@id": "kb:BlueCard",
          "@type": [
            "schema:PaymentMethod"
          ],
          "rdfs:label": {
            "en": [
              "Blue card"
            ],
            "fr": [
              "Carte bleue"
            ]
          }
        },
        {
          "@id": "kb:Cash",
          "@type": [
            "schema:PaymentMethod"
          ],
          "rdfs:label": {
            "en": [
              "Cash"
            ],
            "fr": [
              "Espèce"
            ]
          }
        },
        {
          "@id": "kb:Check",
          "@type": [
            "schema:PaymentMethod"
          ],
          "rdfs:label": {
            "en": [
              "Check"
            ],
            "fr": [
              "Chèque"
            ]
          }
        },
        {
          "@id": "kb:EurocardMastercard",
          "@type": [
            "schema:PaymentMethod"
          ],
          "rdfs:label": {
            "en": [
              "Eurocard - mastercard"
            ],
            "fr": [
              "Eurocard - mastercard"
            ]
          }
        },
        {
          "@id": "kb:HolidayVouchers",
          "@type": [
            "schema:PaymentMethod"
          ],
          "rdfs:label": {
            "en": [
              "Holiday vouchers"
            ],
            "fr": [
              "Chèques vacances"
            ]
          }
        },
        {
          "@id": "kb:Transfers",
          "@type": [
            "schema:PaymentMethod"
          ],
          "rdfs:label": {
            "en": [
              "Transfers"
            ],
            "fr": [
              "Virements"
            ]
          }
        },
        {
          "@id": "kb:Visa",
          "@type": [
            "schema:PaymentMethod"
          ],
          "rdfs:label": {
            "en": [
              "Visa"
            ],
            "fr": [
              "Visa"
            ]
          }
        }
      ],
      "schema:priceSpecification": [
        {
          "@id": "https://data.datatourisme.gouv.fr/2ea5e684-3c43-35d5-b6f8-b990130cde8d",
          "schema:maxPrice": [
            "1380"
          ],
          "schema:minPrice": [
            "1380"
          ],
          "schema:price": "1380",
          "schema:priceCurrency": "EUR",
          "@type": [
            "schema:PriceSpecification"
          ],
          "additionalInformation": {
            "fr": [
              "pour tout le moulin 3jours - 2nuits"
            ]
          }
        },
        {
          "@id": "https://data.datatourisme.gouv.fr/42e64034-7ff0-30c3-9d85-2df6e1c4d336",
          "schema:maxPrice": [
            "40"
          ],
          "schema:minPrice": [
            "40"
          ],
          "schema:price": "40",
          "schema:priceCurrency": "EUR",
          "@type": [
            "schema:PriceSpecification"
          ],
          "additionalInformation": {
            "fr": [
              "forfaitaire"
            ]
          }
        },
        {
          "@id": "https://data.datatourisme.gouv.fr/606abfc9-d40a-3cd9-914d-d7a7f941c141",
          "schema:maxPrice": [
            "740"
          ],
          "schema:minPrice": [
            "740"
          ],
          "schema:price": "740",
          "schema:priceCurrency": "EUR",
          "@type": [
            "schema:PriceSpecification"
          ],
          "additionalInformation": {
            "fr": [
              "de novembre à février pour 1 nuit"
            ]
          }
        }
      ],
      "@type": [
        "schema:Offer",
        "Offer"
      ]
    }
  ],
  "reducedMobilityAccess": true
}