{
  "@id": "https://data.datatourisme.gouv.fr/15/7038dcf7-4820-33ba-bddf-5d44edbb8aa0",
  "dc:identifier": "FMACEN037V50JZFS",
  "schema:endDate": [
    "2020-09-11",
    "2020-10-24"
  ],
  "schema:startDate": [
    "2020-09-11",
    "2020-10-24"
  ],
  "@type": [
    "schema:Event",
    "EntertainmentAndEvent",
    "PointOfInterest"
  ],
  "rdfs:comment": {
    "fr": [
      "Le château-monastère de la Corroirie accueille le Domaine de la Grenadière.  Vivez un moment privilégié : profitez du cadre et découvrez les vins de Montrésor. Thierry Touratier, vigneron, vous raconte l'histoire de ses vins.  Dégustation de 4 vins. Réservation obligatoire. Limité à 20 personnes."
    ]
  },
  "rdfs:label": {
    "fr": [
      "Dégustation \"7 vins 7 lieux insolites\""
    ]
  },
  "creationDate": "2020-07-09",
  "hasAudience": [
    {
      "@id": "kb:Regional",
      "@type": [
        "GeographicReach"
      ],
      "rdfs:label": {
        "en": [
          "Regional"
        ],
        "fr": [
          "Régionale"
        ]
      }
    }
  ],
  "hasBeenCreatedBy": {
    "@id": "https://data.datatourisme.gouv.fr/04c81750-b203-3927-9f84-c974baa96a0c",
    "schema:legalName": "Loches Touraine Châteaux de la Loire",
    "@type": [
      "schema:Organization",
      "foaf:Agent",
      "Agent"
    ]
  },
  "hasBeenPublishedBy": [
    {
      "@id": "https://data.datatourisme.gouv.fr/bba35b4d-022c-3fa7-90a3-07eba818e3a5",
      "schema:legalName": "SIT Centre-Val de Loire",
      "@type": [
        "schema:Organization",
        "foaf:Agent",
        "Agent"
      ]
    }
  ],
  "hasContact": [
    {
      "@id": "https://data.datatourisme.gouv.fr/854ca48b-9fbd-393d-b962-f24e20377efc",
      "schema:email": [
        "marine.desfontaine@loches-valdeloire.com"
      ],
      "schema:telephone": [
        "+33 2 47 91 82 88"
      ],
      "@type": [
        "foaf:Agent",
        "Agent"
      ]
    }
  ],
  "hasDescription": [
    {
      "@id": "https://data.datatourisme.gouv.fr/d98d1bd8-1ec5-363d-baa0-5255afdd1a6b",
      "dc:description": {
        "fr": [
          "Le château-monastère de la Corroirie accueille le Domaine de la Grenadière.  Lorsque le château ferme ses portes, vivez un moment privilégié : profitez du cadre et découvrez les vins de Montrésor. Thierry Touratier, vigneron, vous raconte l'histoire de ses vins.\nDégustation de 4 vins (blanc, rosé, rosé pétillant et rouge) - vente sur place.\nRéservation obligatoire à l'office de tourisme de Loches. Limité à 20 personnes."
        ]
      },
      "@type": [
        "Description"
      ],
      "shortDescription": {
        "fr": [
          "Le château-monastère de la Corroirie accueille le Domaine de la Grenadière.  Vivez un moment privilégié : profitez du cadre et découvrez les vins de Montrésor. Thierry Touratier, vigneron, vous raconte l'histoire de ses vins.  Dégustation de 4 vins. Réservation obligatoire. Limité à 20 personnes."
        ]
      }
    }
  ],
  "hasGeographicReach": [
    {
      "@id": "kb:Regional",
      "@type": [
        "GeographicReach"
      ],
      "rdfs:label": {
        "en": [
          "Regional"
        ],
        "fr": [
          "Régionale"
        ]
      }
    }
  ],
  "hasMainRepresentation": [
    {
      "@id": "https://data.datatourisme.gouv.fr/c2cec60c-947b-3b14-87a6-c7a9afc7d9ef",
      "ebucore:hasAnnotation": [
        {
          "@id": "https://data.datatourisme.gouv.fr/035d95ef-1663-393e-b085-03f760ada72b",
          "ebucore:isCoveredBy": "oui",
          "ebucore:title": {
            "fr": [
              "Château Monastère - Corrorie - Loches -Val de Loire"
            ]
          },
          "@type": [
            "ebucore:Annotation",
            "Annotation"
          ],
          "credits": [
            "L. De Serres"
          ],
          "rightsEndDate": "2024-12-31"
        }
      ],
      "ebucore:hasRelatedResource": [
        {
          "@id": "https://data.datatourisme.gouv.fr/11e0d600-f75a-3b02-8670-cbb149a33849",
          "ebucore:hasMimeType": [
            {
              "@id": "kb:JPEG",
              "@type": [
                "ebucore:MimeType"
              ],
              "rdfs:comment": {
                "fr": [
                  "Image JPEG"
                ]
              },
              "rdfs:label": [
                "image/jpeg"
              ]
            }
          ],
          "ebucore:locator": [
            "https://centre.media.tourinsoft.eu/upload/Chateau-Monastere---Corrorie---Loches--Val-de-Loire.jpg"
          ],
          "@type": [
            "ebucore:Resource"
          ]
        }
      ],
      "@type": [
        "ebucore:EditorialObject"
      ]
    }
  ],
  "hasRepresentation": [
    {
      "@id": "https://data.datatourisme.gouv.fr/4a17ded1-3244-3c97-ab65-57aaef74e3db",
      "ebucore:hasAnnotation": [
        {
          "@id": "https://data.datatourisme.gouv.fr/083c68a6-8860-32cf-a3e4-81da7af0a47f",
          "ebucore:title": {
            "fr": [
              "Château Monastère - Corrorie - Loches -Val de Loire 2"
            ]
          },
          "@type": [
            "ebucore:Annotation",
            "Annotation"
          ],
          "credits": [
            "L. De Serres"
          ],
          "rightsEndDate": "2024-12-31"
        }
      ],
      "ebucore:hasRelatedResource": [
        {
          "@id": "https://data.datatourisme.gouv.fr/d759ebc0-8138-3e79-a1d4-5894e1bc178a",
          "ebucore:hasMimeType": [
            {
              "@id": "kb:JPEG",
              "@type": [
                "ebucore:MimeType"
              ],
              "rdfs:comment": {
                "fr": [
                  "Image JPEG"
                ]
              },
              "rdfs:label": [
                "image/jpeg"
              ]
            }
          ],
          "ebucore:locator": [
            "https://centre.media.tourinsoft.eu/upload/Chateau-Monastere---Corrorie---Loches--Val-de-Loire-2.jpg"
          ],
          "@type": [
            "ebucore:Resource"
          ]
        }
      ],
      "@type": [
        "ebucore:EditorialObject"
      ]
    },
    {
      "@id": "https://data.datatourisme.gouv.fr/4d99b7f5-d8a6-3eee-aea4-8a9b97e91b8a",
      "ebucore:hasAnnotation": [
        {
          "@id": "https://data.datatourisme.gouv.fr/61618c22-105e-3497-9a29-cdb2d436d771",
          "ebucore:title": {
            "fr": [
              "domaine de la grenadière - montrésor vin- val de loire v2"
            ]
          },
          "@type": [
            "ebucore:Annotation",
            "Annotation"
          ],
          "credits": [
            "I. Bardiau"
          ],
          "rightsEndDate": "2029-12-31"
        }
      ],
      "ebucore:hasRelatedResource": [
        {
          "@id": "https://data.datatourisme.gouv.fr/1255a6cf-83b0-388b-8e43-faf234a8493e",
          "ebucore:hasMimeType": [
            {
              "@id": "kb:JPEG",
              "@type": [
                "ebucore:MimeType"
              ],
              "rdfs:comment": {
                "fr": [
                  "Image JPEG"
                ]
              },
              "rdfs:label": [
                "image/jpeg"
              ]
            }
          ],
          "ebucore:locator": [
            "https://centre.media.tourinsoft.eu/upload/domaine-de-la-grenadiere---montresor-vin--val-de-loire-v2-b649690b36274681888cd9955d8f8713.jpg"
          ],
          "@type": [
            "ebucore:Resource"
          ]
        }
      ],
      "@type": [
        "ebucore:EditorialObject"
      ]
    },
    {
      "@id": "https://data.datatourisme.gouv.fr/ad1a4e9c-d505-366f-8616-8c77b758ba46",
      "ebucore:hasAnnotation": [
        {
          "@id": "https://data.datatourisme.gouv.fr/46da7c4a-991f-3c8b-a743-e85ced793755",
          "ebucore:title": {
            "fr": [
              "Château Monastère - Corrorie - Loches -Val de Loire"
            ]
          },
          "@type": [
            "ebucore:Annotation",
            "Annotation"
          ],
          "credits": [
            "L. De Serres"
          ],
          "rightsEndDate": "2024-12-31"
        }
      ],
      "ebucore:hasRelatedResource": [
        {
          "@id": "https://data.datatourisme.gouv.fr/11e0d600-f75a-3b02-8670-cbb149a33849",
          "ebucore:hasMimeType": [
            {
              "@id": "kb:JPEG",
              "@type": [
                "ebucore:MimeType"
              ],
              "rdfs:comment": {
                "fr": [
                  "Image JPEG"
                ]
              },
              "rdfs:label": [
                "image/jpeg"
              ]
            }
          ],
          "ebucore:locator": [
            "https://centre.media.tourinsoft.eu/upload/Chateau-Monastere---Corrorie---Loches--Val-de-Loire.jpg"
          ],
          "@type": [
            "ebucore:Resource"
          ]
        }
      ],
      "@type": [
        "ebucore:EditorialObject"
      ]
    },
    {
      "@id": "https://data.datatourisme.gouv.fr/c2cec60c-947b-3b14-87a6-c7a9afc7d9ef",
      "ebucore:hasAnnotation": [
        {
          "@id": "https://data.datatourisme.gouv.fr/035d95ef-1663-393e-b085-03f760ada72b",
          "ebucore:isCoveredBy": "oui",
          "ebucore:title": {
            "fr": [
              "Château Monastère - Corrorie - Loches -Val de Loire"
            ]
          },
          "@type": [
            "ebucore:Annotation",
            "Annotation"
          ],
          "credits": [
            "L. De Serres"
          ],
          "rightsEndDate": "2024-12-31"
        }
      ],
      "ebucore:hasRelatedResource": [
        {
          "@id": "https://data.datatourisme.gouv.fr/11e0d600-f75a-3b02-8670-cbb149a33849",
          "ebucore:hasMimeType": [
            {
              "@id": "kb:JPEG",
              "@type": [
                "ebucore:MimeType"
              ],
              "rdfs:comment": {
                "fr": [
                  "Image JPEG"
                ]
              },
              "rdfs:label": [
                "image/jpeg"
              ]
            }
          ],
          "ebucore:locator": [
            "https://centre.media.tourinsoft.eu/upload/Chateau-Monastere---Corrorie---Loches--Val-de-Loire.jpg"
          ],
          "@type": [
            "ebucore:Resource"
          ]
        }
      ],
      "@type": [
        "ebucore:EditorialObject"
      ]
    }
  ],
  "hasReview": [
    {
      "@id": "https://data.datatourisme.gouv.fr/4d672591-b642-3982-91a7-b0b7a8872d12",
      "@type": [
        "Review"
      ],
      "hasReviewValue": {
        "@id": "kb:COVID19ProtocolsCommitted",
        "@type": [
          "LabelRating"
        ],
        "rdfs:label": {
          "en": [
            "Committed to official health protocols Covid-19"
          ],
          "fr": [
            "Engagé à respecter les protocoles sanitaires officiels Covid-19"
          ]
        },
        "isCompliantWith": [
          "PointOfInterest"
        ]
      }
    }
  ],
  "isLocatedAt": [
    {
      "@id": "https://data.datatourisme.gouv.fr/485bfc56-5619-3a61-9d46-8d3e016894ad",
      "schema:address": [
        {
          "@id": "https://data.datatourisme.gouv.fr/6e2d9f84-4453-3636-b876-5cab99f88e96",
          "schema:addressLocality": "Montrésor",
          "schema:postalCode": "37460",
          "@type": [
            "schema:PostalAddress",
            "PostalAddress"
          ],
          "hasAddressCity": [
            {
              "@id": "kb:37157",
              "@type": [
                "City"
              ],
              "rdfs:label": {
                "en": [
                  "Montrésor"
                ],
                "fr": [
                  "Montrésor"
                ]
              },
              "insee": "37157",
              "isPartOfDepartment": [
                {
                  "@id": "kb:France2437",
                  "@type": [
                    "Department"
                  ],
                  "rdfs:label": {
                    "en": [
                      "Indre-et-Loire"
                    ],
                    "fr": [
                      "Indre-et-Loire"
                    ]
                  },
                  "insee": "37",
                  "isPartOfRegion": [
                    {
                      "@id": "kb:France24",
                      "@type": [
                        "Region"
                      ],
                      "rdfs:label": {
                        "en": [
                          "Centre-Val de Loire"
                        ],
                        "fr": [
                          "Centre-Val de Loire"
                        ]
                      },
                      "insee": "24",
                      "isPartOfCountry": [
                        {
                          "@id": "kb:France",
                          "@type": [
                            "schema:Country"
                          ],
                          "rdfs:label": {
                            "en": [
                              "France"
                            ],
                            "fr": [
                              "France"
                            ]
                          }
                        }
                      ]
                    }
                  ]
                }
              ]
            }
          ]
        }
      ],
      "schema:geo": {
        "@id": "https://data.datatourisme.gouv.fr/efc62e37-da51-3f04-8ed7-8235d90764ba",
        "schema:latitude": "47.1510826",
        "schema:longitude": "1.13994295",
        "@type": [
          "schema:GeoCoordinates"
        ]
      },
      "@type": [
        "schema:Place",
        "Place"
      ]
    }
  ],
  "lastUpdate": "2020-08-27",
  "lastUpdateDatatourisme": "2020-08-28T04:03:59.906Z",
  "offers": [
    {
      "@id": "https://data.datatourisme.gouv.fr/45d8e845-2996-3341-9b1e-a23df548a059",
      "schema:priceSpecification": [
        {
          "@id": "https://data.datatourisme.gouv.fr/8c4dfe57-2d30-3c45-b720-b3b09208f2d7",
          "schema:minPrice": [
            "10"
          ],
          "schema:price": "10",
          "schema:priceCurrency": "EUR",
          "@type": [
            "schema:PriceSpecification",
            "PriceSpecification"
          ],
          "hasEligiblePolicy": {
            "@id": "kb:BaseRateFullRate",
            "@type": [
              "PricingPolicy"
            ],
            "rdfs:label": {
              "en": [
                "Base rate - full rate"
              ],
              "fr": [
                "Tarif de base - plein tarif"
              ]
            }
          }
        }
      ],
      "@type": [
        "schema:Offer",
        "Offer"
      ]
    }
  ],
  "takesPlaceAt": [
    {
      "@id": "https://data.datatourisme.gouv.fr/5e8f4d09-2144-3339-9e60-c00095d2c0ee",
      "@type": [
        "Period"
      ],
      "endDate": "2020-09-11",
      "endTime": "19:00:00",
      "startDate": "2020-09-11",
      "startTime": "18:00:00"
    },
    {
      "@id": "https://data.datatourisme.gouv.fr/b8896712-4ddb-3dc7-9018-49c2f6c9ab20",
      "@type": [
        "Period"
      ],
      "endDate": "2020-10-24",
      "endTime": "19:00:00",
      "startDate": "2020-10-24",
      "startTime": "18:00:00"
    }
  ]
}