{
  "@id": "https://data.datatourisme.gouv.fr/15/85478a32-7db9-3019-8bdd-96fb178db9eb",
  "dc:identifier": "HOTCEN0370000343",
  "@type": [
    "schema:FoodEstablishment",
    "schema:Hotel",
    "schema:LodgingBusiness",
    "schema:Restaurant",
    "Accommodation",
    "FoodEstablishment",
    "Hotel",
    "HotelRestaurant",
    "HotelTrade",
    "PlaceOfInterest",
    "PointOfInterest",
    "Restaurant"
  ],
  "rdfs:comment": {
    "en": [
      "Not far from the Châteaux of the Loire, 5 minutes from Amboise. A small country inn (former coaching inn) with a large reception room (60 - 70 people), a restaurant (30 people max.), as well as 16 bedrooms. Open all year round."
    ],
    "fr": [
      "Au coeur des châteaux de la Loire, situé à 5 minutes d'Amboise, une petite auberge rustique, ancien relais de diligence, dotée d'une salle de restaurant (30 pers. maxi), ainsi que 14 chambres, situé dans la commune de Pocé sur Cisse à deux pas d'un grand parc, vous accueille tout au long de l'année."
    ]
  },
  "rdfs:label": {
    "en": [
      "Auberge de la Ramberge"
    ],
    "fr": [
      "Auberge de la Ramberge"
    ]
  },
  "allowedPersons": 30,
  "availableLanguage": [
    "en",
    "fr"
  ],
  "creationDate": "2002-11-13",
  "hasBeenCreatedBy": {
    "@id": "https://data.datatourisme.gouv.fr/e8d45b94-7ba3-3b34-95e2-24a98bc212ce",
    "schema:legalName": "OFFICE AMBOISE",
    "@type": [
      "schema:Organization",
      "foaf:Agent",
      "Agent"
    ]
  },
  "hasBeenPublishedBy": [
    {
      "@id": "https://data.datatourisme.gouv.fr/bba35b4d-022c-3fa7-90a3-07eba818e3a5",
      "schema:legalName": "SIT Centre-Val de Loire",
      "@type": [
        "schema:Organization",
        "foaf:Agent",
        "Agent"
      ]
    }
  ],
  "hasBookingContact": [
    {
      "@id": "https://data.datatourisme.gouv.fr/2bdbbda8-e1b0-3e4d-8649-f6576080f231",
      "schema:telephone": [
        "+33 2 47 57 32 48"
      ],
      "@type": [
        "foaf:Agent",
        "Agent"
      ],
      "foaf:homepage": [
        "http://aubergeramberge.com/reserver/"
      ]
    }
  ],
  "hasContact": [
    {
      "@id": "https://data.datatourisme.gouv.fr/2bdbbda8-e1b0-3e4d-8649-f6576080f231",
      "schema:telephone": [
        "+33 2 47 57 32 48"
      ],
      "@type": [
        "foaf:Agent",
        "Agent"
      ],
      "foaf:homepage": [
        "http://aubergeramberge.com/reserver/"
      ]
    },
    {
      "@id": "https://data.datatourisme.gouv.fr/78fd7504-7787-3574-a90d-c4f89c9db3ad",
      "schema:email": [
        "aubergeramberge@aubergeramberge.com"
      ],
      "schema:legalName": "Auberge de la Ramberge",
      "schema:telephone": [
        "+33 2 47 57 32 48"
      ],
      "@type": [
        "schema:Organization",
        "foaf:Agent",
        "Agent"
      ],
      "foaf:homepage": [
        "http://www.aubergeramberge.com/"
      ]
    }
  ],
  "hasDescription": [
    {
      "@id": "https://data.datatourisme.gouv.fr/294a50cc-f89b-393f-805d-298e47705627",
      "dc:description": {
        "en": [
          "Not far from the Châteaux of the Loire, 5 minutes from Amboise. A small country inn (former coaching inn) with a large reception room (60 - 70 people), a restaurant (30 people max.), as well as 16 bedrooms. Open all year round."
        ],
        "fr": [
          "Au coeur des châteaux de la Loire, situé à 5 minutes d'Amboise, une petite auberge rustique, ancien relais de diligence, dotée d'une salle de restaurant (30 pers. maxi), ainsi que 14 chambres, situé dans la commune de Pocé sur Cisse à deux pas d'un grand parc, vous accueille tout au long de l'année."
        ]
      },
      "@type": [
        "Description"
      ],
      "shortDescription": {
        "en": [
          "Not far from the Châteaux of the Loire, 5 minutes from Amboise. A small country inn (former coaching inn) with a large reception room (60 - 70 people), a restaurant (30 people max.), as well as 16 bedrooms. Open all year round."
        ],
        "fr": [
          "Au coeur des châteaux de la Loire, situé à 5 minutes d'Amboise, une petite auberge rustique, ancien relais de diligence, dotée d'une salle de restaurant (30 pers. maxi), ainsi que 14 chambres, situé dans la commune de Pocé sur Cisse à deux pas d'un grand parc, vous accueille tout au long de l'année."
        ]
      }
    }
  ],
  "hasFeature": [
    {
      "@id": "https://data.datatourisme.gouv.fr/1d6b9823-8f0b-3dbd-8ac8-46034133a11f",
      "@type": [
        "schema:PropertyValue",
        "FeatureSpecification"
      ],
      "features": [
        {
          "@id": "kb:BikeGarage",
          "@type": [
            "CommonAmenity"
          ],
          "rdfs:label": {
            "en": [
              "Bike garage"
            ],
            "fr": [
              "Garage à vélo"
            ]
          }
        }
      ]
    },
    {
      "@id": "https://data.datatourisme.gouv.fr/3649eae9-c4b2-3f23-94b4-c48ba67f7f03",
      "@type": [
        "schema:PropertyValue",
        "FeatureSpecification"
      ],
      "features": [
        {
          "@id": "kb:LockedStorageRoom",
          "@type": [
            "CommonAmenity"
          ],
          "rdfs:label": {
            "en": [
              "Locked storage room"
            ],
            "fr": [
              "Local matériel fermé"
            ]
          }
        }
      ]
    },
    {
      "@id": "https://data.datatourisme.gouv.fr/382a229e-6451-3361-b47e-3c1c0d682292",
      "@type": [
        "schema:PropertyValue",
        "FeatureSpecification"
      ],
      "features": [
        {
          "@id": "kb:Fax",
          "@type": [
            "CommonAmenity"
          ],
          "rdfs:label": {
            "en": [
              "Fax"
            ],
            "fr": [
              "Fax"
            ]
          }
        }
      ]
    },
    {
      "@id": "https://data.datatourisme.gouv.fr/6d762816-db41-3ab9-9ab0-afb2d8471c87",
      "@type": [
        "schema:PropertyValue",
        "FeatureSpecification"
      ],
      "features": [
        {
          "@id": "kb:Restaurant",
          "@type": [
            "CommonAmenity"
          ],
          "rdfs:label": {
            "en": [
              "Restaurant"
            ],
            "fr": [
              "Restaurant"
            ]
          }
        }
      ]
    },
    {
      "@id": "https://data.datatourisme.gouv.fr/a1efbae8-3512-36dd-8d5b-79286663d111",
      "schema:value": "15",
      "@type": [
        "schema:PropertyValue",
        "FeatureSpecification"
      ],
      "features": [
        {
          "@id": "kb:Bedroom",
          "@type": [
            "AccommodationAmenity",
            "AccommodationPricingOffer"
          ],
          "rdfs:label": {
            "en": [
              "Bedroom"
            ],
            "fr": [
              "Chambre"
            ]
          }
        }
      ]
    },
    {
      "@id": "https://data.datatourisme.gouv.fr/b5aeee97-c905-350a-b47e-5eab8eddae3c",
      "@type": [
        "schema:PropertyValue",
        "FeatureSpecification"
      ],
      "features": [
        {
          "@id": "kb:CarPark",
          "@type": [
            "CommonAmenity"
          ],
          "rdfs:label": {
            "en": [
              "Car park"
            ],
            "fr": [
              "Parking"
            ]
          }
        }
      ]
    }
  ],
  "hasMainRepresentation": [
    {
      "@id": "https://data.datatourisme.gouv.fr/284b7658-e216-34f5-b64f-5be09194e32e",
      "ebucore:hasAnnotation": [
        {
          "@id": "https://data.datatourisme.gouv.fr/cdc74f8a-ca4a-3b81-a2fb-d6402205032b",
          "ebucore:isCoveredBy": "oui",
          "ebucore:title": {
            "fr": [
              "Auberge de la Ramberge"
            ]
          },
          "@type": [
            "ebucore:Annotation",
            "Annotation"
          ],
          "credits": [
            "© Droits réservés"
          ],
          "rightsEndDate": "2018-08-31"
        }
      ],
      "ebucore:hasRelatedResource": [
        {
          "@id": "https://data.datatourisme.gouv.fr/93bcc2d5-87ae-30b7-9db0-b12af0bf3358",
          "ebucore:hasMimeType": [
            {
              "@id": "kb:JPEG",
              "@type": [
                "ebucore:MimeType"
              ],
              "rdfs:comment": {
                "fr": [
                  "Image JPEG"
                ]
              },
              "rdfs:label": [
                "image/jpeg"
              ]
            }
          ],
          "ebucore:locator": [
            "https://centre.media.tourinsoft.eu/upload/Auberge-de-la-Ramberge-1.jpg"
          ],
          "@type": [
            "ebucore:Resource"
          ]
        }
      ],
      "@type": [
        "ebucore:EditorialObject"
      ]
    }
  ],
  "hasRepresentation": [
    {
      "@id": "https://data.datatourisme.gouv.fr/1f2cb236-fc71-3e23-8d19-24392e711a64",
      "ebucore:hasAnnotation": [
        {
          "@id": "https://data.datatourisme.gouv.fr/8187709d-2516-371e-9dab-3d9932c082a0",
          "ebucore:isCoveredBy": "oui",
          "ebucore:title": {
            "fr": [
              "Auberge de la Ramberge (3)"
            ]
          },
          "@type": [
            "ebucore:Annotation",
            "Annotation"
          ],
          "credits": [
            "Droits réservés"
          ],
          "rightsEndDate": "2018-05-31"
        }
      ],
      "ebucore:hasRelatedResource": [
        {
          "@id": "https://data.datatourisme.gouv.fr/b1e62895-531d-3859-af29-df437055a8b5",
          "ebucore:hasMimeType": [
            {
              "@id": "kb:JPEG",
              "@type": [
                "ebucore:MimeType"
              ],
              "rdfs:comment": {
                "fr": [
                  "Image JPEG"
                ]
              },
              "rdfs:label": [
                "image/jpeg"
              ]
            }
          ],
          "ebucore:locator": [
            "https://centre.media.tourinsoft.eu/upload/Auberge-de-la-Ramberge--3-.jpg"
          ],
          "@type": [
            "ebucore:Resource"
          ]
        }
      ],
      "@type": [
        "ebucore:EditorialObject"
      ]
    },
    {
      "@id": "https://data.datatourisme.gouv.fr/284b7658-e216-34f5-b64f-5be09194e32e",
      "ebucore:hasAnnotation": [
        {
          "@id": "https://data.datatourisme.gouv.fr/cdc74f8a-ca4a-3b81-a2fb-d6402205032b",
          "ebucore:isCoveredBy": "oui",
          "ebucore:title": {
            "fr": [
              "Auberge de la Ramberge"
            ]
          },
          "@type": [
            "ebucore:Annotation",
            "Annotation"
          ],
          "credits": [
            "© Droits réservés"
          ],
          "rightsEndDate": "2018-08-31"
        }
      ],
      "ebucore:hasRelatedResource": [
        {
          "@id": "https://data.datatourisme.gouv.fr/93bcc2d5-87ae-30b7-9db0-b12af0bf3358",
          "ebucore:hasMimeType": [
            {
              "@id": "kb:JPEG",
              "@type": [
                "ebucore:MimeType"
              ],
              "rdfs:comment": {
                "fr": [
                  "Image JPEG"
                ]
              },
              "rdfs:label": [
                "image/jpeg"
              ]
            }
          ],
          "ebucore:locator": [
            "https://centre.media.tourinsoft.eu/upload/Auberge-de-la-Ramberge-1.jpg"
          ],
          "@type": [
            "ebucore:Resource"
          ]
        }
      ],
      "@type": [
        "ebucore:EditorialObject"
      ]
    },
    {
      "@id": "https://data.datatourisme.gouv.fr/a1bca12e-2958-3311-979c-9fac17d910aa",
      "ebucore:hasAnnotation": [
        {
          "@id": "https://data.datatourisme.gouv.fr/4eaadf36-d3e7-3f16-9e15-51a9eb6862da",
          "ebucore:isCoveredBy": "oui",
          "ebucore:title": {
            "fr": [
              "Auberge de la Ramberge (2)"
            ]
          },
          "@type": [
            "ebucore:Annotation",
            "Annotation"
          ],
          "credits": [
            "Droits réservés"
          ],
          "rightsEndDate": "2018-05-31"
        }
      ],
      "ebucore:hasRelatedResource": [
        {
          "@id": "https://data.datatourisme.gouv.fr/24d8a8ff-30ec-38c0-9cbb-1ae8171f13bd",
          "ebucore:hasMimeType": [
            {
              "@id": "kb:JPEG",
              "@type": [
                "ebucore:MimeType"
              ],
              "rdfs:comment": {
                "fr": [
                  "Image JPEG"
                ]
              },
              "rdfs:label": [
                "image/jpeg"
              ]
            }
          ],
          "ebucore:locator": [
            "https://centre.media.tourinsoft.eu/upload/Auberge-de-la-Ramberge--2-.jpg"
          ],
          "@type": [
            "ebucore:Resource"
          ]
        }
      ],
      "@type": [
        "ebucore:EditorialObject"
      ]
    },
    {
      "@id": "https://data.datatourisme.gouv.fr/c3a22c51-8879-3fb0-bef3-7cf8341543f0",
      "ebucore:hasAnnotation": [
        {
          "@id": "https://data.datatourisme.gouv.fr/4570bb9a-c75e-3f3f-bfa8-d0e9cb079485",
          "ebucore:isCoveredBy": "oui",
          "ebucore:title": {
            "fr": [
              "Auberge de la Ramberge"
            ]
          },
          "@type": [
            "ebucore:Annotation",
            "Annotation"
          ],
          "credits": [
            "Droits réservés"
          ],
          "rightsEndDate": "2018-05-31"
        }
      ],
      "ebucore:hasRelatedResource": [
        {
          "@id": "https://data.datatourisme.gouv.fr/0fd8ed19-b8e3-3455-a3c5-cf03a9f7aa40",
          "ebucore:hasMimeType": [
            {
              "@id": "kb:JPEG",
              "@type": [
                "ebucore:MimeType"
              ],
              "rdfs:comment": {
                "fr": [
                  "Image JPEG"
                ]
              },
              "rdfs:label": [
                "image/jpeg"
              ]
            }
          ],
          "ebucore:locator": [
            "https://centre.media.tourinsoft.eu/upload/Auberge-de-la-Ramberge-2.jpg"
          ],
          "@type": [
            "ebucore:Resource"
          ]
        }
      ],
      "@type": [
        "ebucore:EditorialObject"
      ]
    }
  ],
  "hasReview": [
    {
      "@id": "https://data.datatourisme.gouv.fr/50877d43-0356-3f59-8645-d2679f975701",
      "@type": [
        "Review"
      ],
      "hasReviewValue": {
        "@id": "kb:ScaleRating_1etoile",
        "schema:ratingValue": "1.0",
        "@type": [
          "ScaleRating"
        ],
        "rdfs:label": {
          "en": [
            "1 étoile"
          ],
          "fr": [
            "1 étoile"
          ]
        },
        "isCompliantWith": [
          "CampingAndCaravanning",
          "ClubOrHolidayVillage",
          "HolidayCentre",
          "Hotel",
          "SelfCateringAccommodation"
        ]
      }
    }
  ],
  "isLocatedAt": [
    {
      "@id": "https://data.datatourisme.gouv.fr/68738ad2-2972-37fd-a9ab-f679ef131514",
      "schema:address": [
        {
          "@id": "https://data.datatourisme.gouv.fr/15bbb90f-3e65-3734-ab09-bb159f44328f",
          "schema:addressLocality": "Pocé-sur-Cisse",
          "schema:postalCode": "37530",
          "schema:streetAddress": [
            "9 route de St Ouen les Vignes"
          ],
          "@type": [
            "schema:PostalAddress",
            "PostalAddress"
          ],
          "hasAddressCity": [
            {
              "@id": "kb:37185",
              "@type": [
                "City"
              ],
              "rdfs:label": {
                "en": [
                  "Pocé-sur-Cisse"
                ],
                "fr": [
                  "Pocé-sur-Cisse"
                ]
              },
              "insee": "37185",
              "isPartOfDepartment": [
                {
                  "@id": "kb:France2437",
                  "@type": [
                    "Department"
                  ],
                  "rdfs:label": {
                    "en": [
                      "Indre-et-Loire"
                    ],
                    "fr": [
                      "Indre-et-Loire"
                    ]
                  },
                  "insee": "37",
                  "isPartOfRegion": [
                    {
                      "@id": "kb:France24",
                      "@type": [
                        "Region"
                      ],
                      "rdfs:label": {
                        "en": [
                          "Centre-Val de Loire"
                        ],
                        "fr": [
                          "Centre-Val de Loire"
                        ]
                      },
                      "insee": "24",
                      "isPartOfCountry": [
                        {
                          "@id": "kb:France",
                          "@type": [
                            "schema:Country"
                          ],
                          "rdfs:label": {
                            "en": [
                              "France"
                            ],
                            "fr": [
                              "France"
                            ]
                          }
                        }
                      ]
                    }
                  ]
                }
              ]
            }
          ]
        }
      ],
      "schema:geo": {
        "@id": "https://data.datatourisme.gouv.fr/31c24347-6ea9-380e-bc1a-5fd2bbc287fb",
        "schema:latitude": "47.4437542",
        "schema:longitude": "0.990588",
        "@type": [
          "schema:GeoCoordinates"
        ]
      },
      "schema:openingHoursSpecification": [
        {
          "@id": "https://data.datatourisme.gouv.fr/041a0eb6-bbd9-3913-8cb6-c890ccd9deab",
          "schema:closes": "21:00:00",
          "schema:dayOfWeek": [
            {
              "@id": "schema:Thursday",
              "@type": [
                "schema:DayOfWeek"
              ],
              "rdfs:label": {
                "en": [
                  "Thursday"
                ],
                "fr": [
                  "Jeudi"
                ]
              }
            }
          ],
          "schema:opens": "17:00:00",
          "schema:validFrom": "2020-01-01T00:00:00",
          "schema:validThrough": "2020-12-31T00:00:00",
          "@type": [
            "schema:OpeningHoursSpecification"
          ]
        },
        {
          "@id": "https://data.datatourisme.gouv.fr/19a0476d-97fb-34f1-8853-cd16788737e9",
          "schema:closes": "11:00:00",
          "schema:dayOfWeek": [
            {
              "@id": "schema:Thursday",
              "@type": [
                "schema:DayOfWeek"
              ],
              "rdfs:label": {
                "en": [
                  "Thursday"
                ],
                "fr": [
                  "Jeudi"
                ]
              }
            }
          ],
          "schema:opens": "07:00:00",
          "schema:validFrom": "2020-01-01T00:00:00",
          "schema:validThrough": "2020-12-31T00:00:00",
          "@type": [
            "schema:OpeningHoursSpecification"
          ]
        },
        {
          "@id": "https://data.datatourisme.gouv.fr/3a3fd0d1-eedd-3138-a3ba-b1afe2883bdc",
          "schema:closes": "11:00:00",
          "schema:dayOfWeek": [
            {
              "@id": "schema:Wednesday",
              "@type": [
                "schema:DayOfWeek"
              ],
              "rdfs:label": {
                "en": [
                  "Wednesday"
                ],
                "fr": [
                  "Mercredi"
                ]
              }
            }
          ],
          "schema:opens": "07:00:00",
          "schema:validFrom": "2020-01-01T00:00:00",
          "schema:validThrough": "2020-12-31T00:00:00",
          "@type": [
            "schema:OpeningHoursSpecification"
          ]
        },
        {
          "@id": "https://data.datatourisme.gouv.fr/69808ce4-d69d-3767-828e-738a9fc3ef1a",
          "schema:closes": "11:00:00",
          "schema:dayOfWeek": [
            {
              "@id": "schema:Sunday",
              "@type": [
                "schema:DayOfWeek"
              ],
              "rdfs:label": {
                "en": [
                  "Sunday"
                ],
                "fr": [
                  "Dimanche"
                ]
              }
            }
          ],
          "schema:opens": "07:00:00",
          "schema:validFrom": "2020-01-01T00:00:00",
          "schema:validThrough": "2020-12-31T00:00:00",
          "@type": [
            "schema:OpeningHoursSpecification"
          ]
        },
        {
          "@id": "https://data.datatourisme.gouv.fr/700d0f47-3422-3b06-969a-c6cf109b5d7c",
          "schema:closes": "21:00:00",
          "schema:dayOfWeek": [
            {
              "@id": "schema:Saturday",
              "@type": [
                "schema:DayOfWeek"
              ],
              "rdfs:label": {
                "en": [
                  "Saturday"
                ],
                "fr": [
                  "Samedi"
                ]
              }
            }
          ],
          "schema:opens": "17:00:00",
          "schema:validFrom": "2020-01-01T00:00:00",
          "schema:validThrough": "2020-12-31T00:00:00",
          "@type": [
            "schema:OpeningHoursSpecification"
          ]
        },
        {
          "@id": "https://data.datatourisme.gouv.fr/89fcb7f9-5ac2-382a-ac56-b10cc04f425e",
          "schema:closes": "11:00:00",
          "schema:dayOfWeek": [
            {
              "@id": "schema:Tuesday",
              "@type": [
                "schema:DayOfWeek"
              ],
              "rdfs:label": {
                "en": [
                  "Tuesday"
                ],
                "fr": [
                  "Mardi"
                ]
              }
            }
          ],
          "schema:opens": "07:00:00",
          "schema:validFrom": "2020-01-01T00:00:00",
          "schema:validThrough": "2020-12-31T00:00:00",
          "@type": [
            "schema:OpeningHoursSpecification"
          ]
        },
        {
          "@id": "https://data.datatourisme.gouv.fr/9548a3a4-c4b4-3cb1-8620-4b37e86b089a",
          "schema:closes": "11:00:00",
          "schema:dayOfWeek": [
            {
              "@id": "schema:Friday",
              "@type": [
                "schema:DayOfWeek"
              ],
              "rdfs:label": {
                "en": [
                  "Friday"
                ],
                "fr": [
                  "Vendredi"
                ]
              }
            }
          ],
          "schema:opens": "07:00:00",
          "schema:validFrom": "2020-01-01T00:00:00",
          "schema:validThrough": "2020-12-31T00:00:00",
          "@type": [
            "schema:OpeningHoursSpecification"
          ]
        },
        {
          "@id": "https://data.datatourisme.gouv.fr/aa9582e8-6bdd-38e1-97e6-129777abac67",
          "schema:closes": "21:00:00",
          "schema:dayOfWeek": [
            {
              "@id": "schema:Tuesday",
              "@type": [
                "schema:DayOfWeek"
              ],
              "rdfs:label": {
                "en": [
                  "Tuesday"
                ],
                "fr": [
                  "Mardi"
                ]
              }
            }
          ],
          "schema:opens": "17:00:00",
          "schema:validFrom": "2020-01-01T00:00:00",
          "schema:validThrough": "2020-12-31T00:00:00",
          "@type": [
            "schema:OpeningHoursSpecification"
          ]
        },
        {
          "@id": "https://data.datatourisme.gouv.fr/b70814cd-4ec6-3a73-9b41-a4e1dcedfb5a",
          "schema:closes": "21:00:00",
          "schema:dayOfWeek": [
            {
              "@id": "schema:Monday",
              "@type": [
                "schema:DayOfWeek"
              ],
              "rdfs:label": {
                "en": [
                  "Monday"
                ],
                "fr": [
                  "Lundi"
                ]
              }
            }
          ],
          "schema:opens": "17:00:00",
          "schema:validFrom": "2020-01-01T00:00:00",
          "schema:validThrough": "2020-12-31T00:00:00",
          "@type": [
            "schema:OpeningHoursSpecification"
          ]
        },
        {
          "@id": "https://data.datatourisme.gouv.fr/bc3723d7-3e9d-31cf-9228-9b995ffc49ca",
          "schema:closes": "21:00:00",
          "schema:dayOfWeek": [
            {
              "@id": "schema:Wednesday",
              "@type": [
                "schema:DayOfWeek"
              ],
              "rdfs:label": {
                "en": [
                  "Wednesday"
                ],
                "fr": [
                  "Mercredi"
                ]
              }
            }
          ],
          "schema:opens": "17:00:00",
          "schema:validFrom": "2020-01-01T00:00:00",
          "schema:validThrough": "2020-12-31T00:00:00",
          "@type": [
            "schema:OpeningHoursSpecification"
          ]
        },
        {
          "@id": "https://data.datatourisme.gouv.fr/c59bdae7-7691-3c91-be2e-6b0ca31b6026",
          "schema:closes": "11:00:00",
          "schema:dayOfWeek": [
            {
              "@id": "schema:Saturday",
              "@type": [
                "schema:DayOfWeek"
              ],
              "rdfs:label": {
                "en": [
                  "Saturday"
                ],
                "fr": [
                  "Samedi"
                ]
              }
            }
          ],
          "schema:opens": "07:00:00",
          "schema:validFrom": "2020-01-01T00:00:00",
          "schema:validThrough": "2020-12-31T00:00:00",
          "@type": [
            "schema:OpeningHoursSpecification"
          ]
        },
        {
          "@id": "https://data.datatourisme.gouv.fr/caa0ce82-7b8f-3f23-b8a9-afa7667f37a7",
          "schema:closes": "21:00:00",
          "schema:dayOfWeek": [
            {
              "@id": "schema:Friday",
              "@type": [
                "schema:DayOfWeek"
              ],
              "rdfs:label": {
                "en": [
                  "Friday"
                ],
                "fr": [
                  "Vendredi"
                ]
              }
            }
          ],
          "schema:opens": "17:00:00",
          "schema:validFrom": "2020-01-01T00:00:00",
          "schema:validThrough": "2020-12-31T00:00:00",
          "@type": [
            "schema:OpeningHoursSpecification"
          ]
        }
      ],
      "@type": [
        "schema:Place",
        "Place"
      ],
      "internetAccess": true,
      "petsAllowed": true
    }
  ],
  "lastUpdate": "2020-07-30",
  "lastUpdateDatatourisme": "2020-07-31T09:14:02.62Z",
  "offers": [
    {
      "@id": "https://data.datatourisme.gouv.fr/d7b0bf5c-ad90-390d-96f3-3dc65d8dfafe",
      "schema:acceptedPaymentMethod": [
        {
          "@id": "kb:BlueCard",
          "@type": [
            "schema:PaymentMethod"
          ],
          "rdfs:label": {
            "en": [
              "Blue card"
            ],
            "fr": [
              "Carte bleue"
            ]
          }
        },
        {
          "@id": "kb:Cash",
          "@type": [
            "schema:PaymentMethod"
          ],
          "rdfs:label": {
            "en": [
              "Cash"
            ],
            "fr": [
              "Espèce"
            ]
          }
        },
        {
          "@id": "kb:EurocardMastercard",
          "@type": [
            "schema:PaymentMethod"
          ],
          "rdfs:label": {
            "en": [
              "Eurocard - mastercard"
            ],
            "fr": [
              "Eurocard - mastercard"
            ]
          }
        },
        {
          "@id": "kb:HolidayVouchers",
          "@type": [
            "schema:PaymentMethod"
          ],
          "rdfs:label": {
            "en": [
              "Holiday vouchers"
            ],
            "fr": [
              "Chèques vacances"
            ]
          }
        },
        {
          "@id": "kb:Visa",
          "@type": [
            "schema:PaymentMethod"
          ],
          "rdfs:label": {
            "en": [
              "Visa"
            ],
            "fr": [
              "Visa"
            ]
          }
        }
      ],
      "@type": [
        "schema:Offer",
        "Offer"
      ]
    }
  ],
  "reducedMobilityAccess": false
}