{
  "@id": "https://data.datatourisme.gouv.fr/15/f4a382e2-58ff-33e1-9a13-901c2d8dc4ec",
  "dc:identifier": "ASCCEN037FS0012B",
  "@type": [
    "schema:Product",
    "Course",
    "FirstPractice",
    "IntroductionCourse",
    "PlaceOfInterest",
    "PointOfInterest",
    "Practice",
    "Product",
    "SportsAndLeisurePlace"
  ],
  "rdfs:comment": {
    "en": [
      "Equipped with the latest generation of microlights and at an easily accessible location, our company provides you with an opportunity to take a maiden flight, in addition to Loire castle flight excursions and flight tours on a modern, comfortable and secure aircraft."
    ],
    "fr": [
      "Dotée de la dernière génération d'ULM et située à proximité des grands axes routiers, notre société vous offre la possibilité de faire des baptêmes de l'air, les survols des châteaux de la Loire et des circuits aériens à bord d'un appareil moderne, confortable et sécurisé."
    ]
  },
  "rdfs:label": {
    "en": [
      "Albatros Aviation"
    ],
    "fr": [
      "Albatros Aviation"
    ]
  },
  "availableLanguage": [
    "ar",
    "en",
    "fr",
    "it"
  ],
  "creationDate": "2012-10-23",
  "hasBeenCreatedBy": {
    "@id": "https://data.datatourisme.gouv.fr/14364bf3-4c6c-3c78-b968-8f358561fe97",
    "schema:legalName": "Tours Val de Loire Tourisme",
    "@type": [
      "schema:Organization",
      "foaf:Agent",
      "Agent"
    ]
  },
  "hasBeenPublishedBy": [
    {
      "@id": "https://data.datatourisme.gouv.fr/bba35b4d-022c-3fa7-90a3-07eba818e3a5",
      "schema:legalName": "SIT Centre-Val de Loire",
      "@type": [
        "schema:Organization",
        "foaf:Agent",
        "Agent"
      ]
    }
  ],
  "hasContact": [
    {
      "@id": "https://data.datatourisme.gouv.fr/c53cc75f-3b8a-3a9b-a13c-47e83e4cbd6a",
      "schema:address": [
        {
          "@id": "https://data.datatourisme.gouv.fr/094ef756-7d63-356d-bd5c-f7fc8ac9f6aa",
          "schema:addressLocality": "Joué-lès-Tours",
          "schema:postalCode": "37300",
          "@type": [
            "schema:PostalAddress",
            "PostalAddress"
          ],
          "hasAddressCity": [
            {
              "@id": "kb:37122",
              "@type": [
                "City"
              ],
              "rdfs:label": {
                "en": [
                  "Joué-lès-Tours"
                ],
                "fr": [
                  "Joué-lès-Tours"
                ]
              },
              "insee": "37122",
              "isPartOfDepartment": [
                {
                  "@id": "kb:France2437",
                  "@type": [
                    "Department"
                  ],
                  "rdfs:label": {
                    "en": [
                      "Indre-et-Loire"
                    ],
                    "fr": [
                      "Indre-et-Loire"
                    ]
                  },
                  "insee": "37",
                  "isPartOfRegion": [
                    {
                      "@id": "kb:France24",
                      "@type": [
                        "Region"
                      ],
                      "rdfs:label": {
                        "en": [
                          "Centre-Val de Loire"
                        ],
                        "fr": [
                          "Centre-Val de Loire"
                        ]
                      },
                      "insee": "24",
                      "isPartOfCountry": [
                        {
                          "@id": "kb:France",
                          "@type": [
                            "schema:Country"
                          ],
                          "rdfs:label": {
                            "en": [
                              "France"
                            ],
                            "fr": [
                              "France"
                            ]
                          }
                        }
                      ]
                    }
                  ]
                }
              ]
            }
          ]
        }
      ],
      "schema:email": [
        "abdoubadr37@gmail.com"
      ],
      "schema:legalName": "ALBATROS AVIATION",
      "schema:telephone": [
        "+33 6 73 52 70 44"
      ],
      "@type": [
        "schema:Organization",
        "foaf:Agent",
        "Agent"
      ]
    }
  ],
  "hasDescription": [
    {
      "@id": "https://data.datatourisme.gouv.fr/ec00d56b-aaac-3094-b34b-5c1b8367e7e2",
      "dc:description": {
        "en": [
          "Equipped with the latest generation of microlights and at an easily accessible location, our company provides you with an opportunity to take a maiden flight, in addition to Loire castle flight excursions and flight tours on a modern, comfortable and secure aircraft."
        ],
        "fr": [
          "Dotée de la dernière génération d'ULM et située à proximité des grands axes routiers, notre société vous offre la possibilité de faire des baptêmes de l'air, les survols des châteaux de la Loire et des circuits aériens à bord d'un appareil moderne, confortable et sécurisé."
        ]
      },
      "@type": [
        "Description"
      ],
      "shortDescription": {
        "en": [
          "Equipped with the latest generation of microlights and at an easily accessible location, our company provides you with an opportunity to take a maiden flight, in addition to Loire castle flight excursions and flight tours on a modern, comfortable and secure aircraft."
        ],
        "fr": [
          "Dotée de la dernière génération d'ULM et située à proximité des grands axes routiers, notre société vous offre la possibilité de faire des baptêmes de l'air, les survols des châteaux de la Loire et des circuits aériens à bord d'un appareil moderne, confortable et sécurisé."
        ]
      }
    }
  ],
  "hasMainRepresentation": [
    {
      "@id": "https://data.datatourisme.gouv.fr/e02da0f4-f39d-3193-9f66-dbbbc2c16428",
      "ebucore:hasAnnotation": [
        {
          "@id": "https://data.datatourisme.gouv.fr/fe44d4e5-7628-3ff9-9a20-4258452c7641",
          "ebucore:title": {
            "fr": [
              "Albatros"
            ]
          },
          "@type": [
            "ebucore:Annotation"
          ],
          "credits": [
            "© Droits réservés"
          ]
        }
      ],
      "ebucore:hasRelatedResource": [
        {
          "@id": "https://data.datatourisme.gouv.fr/a4328efa-de6c-3836-ac6b-dcb949e64c3c",
          "ebucore:hasMimeType": [
            {
              "@id": "kb:JPEG",
              "@type": [
                "ebucore:MimeType"
              ],
              "rdfs:comment": {
                "fr": [
                  "Image JPEG"
                ]
              },
              "rdfs:label": [
                "image/jpeg"
              ]
            }
          ],
          "ebucore:locator": [
            "https://centre.media.tourinsoft.eu/upload/Albatros-0123456789.jpg"
          ],
          "@type": [
            "ebucore:Resource"
          ]
        }
      ],
      "@type": [
        "ebucore:EditorialObject"
      ]
    }
  ],
  "hasRepresentation": [
    {
      "@id": "https://data.datatourisme.gouv.fr/e02da0f4-f39d-3193-9f66-dbbbc2c16428",
      "ebucore:hasAnnotation": [
        {
          "@id": "https://data.datatourisme.gouv.fr/fe44d4e5-7628-3ff9-9a20-4258452c7641",
          "ebucore:title": {
            "fr": [
              "Albatros"
            ]
          },
          "@type": [
            "ebucore:Annotation"
          ],
          "credits": [
            "© Droits réservés"
          ]
        }
      ],
      "ebucore:hasRelatedResource": [
        {
          "@id": "https://data.datatourisme.gouv.fr/a4328efa-de6c-3836-ac6b-dcb949e64c3c",
          "ebucore:hasMimeType": [
            {
              "@id": "kb:JPEG",
              "@type": [
                "ebucore:MimeType"
              ],
              "rdfs:comment": {
                "fr": [
                  "Image JPEG"
                ]
              },
              "rdfs:label": [
                "image/jpeg"
              ]
            }
          ],
          "ebucore:locator": [
            "https://centre.media.tourinsoft.eu/upload/Albatros-0123456789.jpg"
          ],
          "@type": [
            "ebucore:Resource"
          ]
        }
      ],
      "@type": [
        "ebucore:EditorialObject"
      ]
    }
  ],
  "hasTheme": [
    {
      "@id": "kb:Ulm",
      "@type": [
        "SportsTheme"
      ],
      "rdfs:label": {
        "en": [
          "Ulm"
        ],
        "fr": [
          "Ulm"
        ]
      }
    }
  ],
  "isLocatedAt": [
    {
      "@id": "https://data.datatourisme.gouv.fr/12f162e8-5df8-39e6-86d8-969746b4cfb6",
      "schema:address": [
        {
          "@id": "https://data.datatourisme.gouv.fr/17d805ed-aacd-33e1-8e67-8835d6b57994",
          "schema:addressLocality": "Joué-lès-Tours",
          "schema:postalCode": "37300",
          "schema:streetAddress": [
            "6 rue Charles Tellier"
          ],
          "@type": [
            "schema:PostalAddress",
            "PostalAddress"
          ],
          "hasAddressCity": [
            {
              "@id": "kb:37122",
              "@type": [
                "City"
              ],
              "rdfs:label": {
                "en": [
                  "Joué-lès-Tours"
                ],
                "fr": [
                  "Joué-lès-Tours"
                ]
              },
              "insee": "37122",
              "isPartOfDepartment": [
                {
                  "@id": "kb:France2437",
                  "@type": [
                    "Department"
                  ],
                  "rdfs:label": {
                    "en": [
                      "Indre-et-Loire"
                    ],
                    "fr": [
                      "Indre-et-Loire"
                    ]
                  },
                  "insee": "37",
                  "isPartOfRegion": [
                    {
                      "@id": "kb:France24",
                      "@type": [
                        "Region"
                      ],
                      "rdfs:label": {
                        "en": [
                          "Centre-Val de Loire"
                        ],
                        "fr": [
                          "Centre-Val de Loire"
                        ]
                      },
                      "insee": "24",
                      "isPartOfCountry": [
                        {
                          "@id": "kb:France",
                          "@type": [
                            "schema:Country"
                          ],
                          "rdfs:label": {
                            "en": [
                              "France"
                            ],
                            "fr": [
                              "France"
                            ]
                          }
                        }
                      ]
                    }
                  ]
                }
              ]
            }
          ]
        }
      ],
      "schema:geo": {
        "@id": "https://data.datatourisme.gouv.fr/0f6301ad-b186-3102-ad9a-1d97448a1f22",
        "schema:latitude": "47.3472578",
        "schema:longitude": "0.6603493",
        "@type": [
          "schema:GeoCoordinates"
        ]
      },
      "@type": [
        "schema:Place",
        "Place"
      ]
    }
  ],
  "lastUpdate": "2020-01-02",
  "lastUpdateDatatourisme": "2020-07-14T05:28:05.27Z",
  "offers": [
    {
      "@id": "https://data.datatourisme.gouv.fr/b1bf2142-44b8-30c4-b293-7d46da7968d8",
      "schema:acceptedPaymentMethod": [
        {
          "@id": "kb:Cash",
          "@type": [
            "schema:PaymentMethod"
          ],
          "rdfs:label": {
            "en": [
              "Cash"
            ],
            "fr": [
              "Espèce"
            ]
          }
        },
        {
          "@id": "kb:Check",
          "@type": [
            "schema:PaymentMethod"
          ],
          "rdfs:label": {
            "en": [
              "Check"
            ],
            "fr": [
              "Chèque"
            ]
          }
        },
        {
          "@id": "kb:HolidayVouchers",
          "@type": [
            "schema:PaymentMethod"
          ],
          "rdfs:label": {
            "en": [
              "Holiday vouchers"
            ],
            "fr": [
              "Chèques vacances"
            ]
          }
        },
        {
          "@id": "kb:Transfers",
          "@type": [
            "schema:PaymentMethod"
          ],
          "rdfs:label": {
            "en": [
              "Transfers"
            ],
            "fr": [
              "Virements"
            ]
          }
        }
      ],
      "schema:priceSpecification": [
        {
          "@id": "https://data.datatourisme.gouv.fr/6af49ca9-458a-39f8-85fd-3552cfe73fd8",
          "schema:priceCurrency": "EUR",
          "@type": [
            "schema:PriceSpecification",
            "PriceSpecification"
          ],
          "hasEligiblePolicy": {
            "@id": "kb:BaseRateFullRate",
            "@type": [
              "PricingPolicy"
            ],
            "rdfs:label": {
              "en": [
                "Base rate - full rate"
              ],
              "fr": [
                "Tarif de base - plein tarif"
              ]
            }
          }
        }
      ],
      "@type": [
        "schema:Offer",
        "Offer"
      ]
    }
  ]
}